{
    "2014-08-01": [
        {
            "title": "U.S. Seeks Release of Couple in Qatar, Creating Tensions With a Crucial Arab Ally ",
            "url": "https://www.nytimes.com/2014/08/01/world/middleeast/us-seeks-couples-release-in-qatar-creating-tensions-with-a-crucial-arab-ally.html",
            "published_date": "2014-08-01T00:21:53+0000",
            "category": "World",
            "abstract": "The State Department asked Qatar to lift a travel ban against an American couple being held in connection with the death of their adopted daughter.",
            "image_url": null
        },
        {
            "title": "Ancient Haven for Refugees Sees Signs of Strain",
            "url": "https://www.nytimes.com/2014/08/01/world/europe/syrian-refugees-in-turkey-ancient-haven-sees-signs-of-strain-government-relocates-displaced-to-camps-in-south.html",
            "published_date": "2014-08-01T00:44:31+0000",
            "category": "World",
            "abstract": "Struggling to accommodate the thousands fleeing civil war in Syria, the Turkish government has quietly begun moving them to camps outside of the cities.",
            "image_url": "https://www.nytimes.com/images/2014/08/01/world/TURKEY/TURKEY-articleLarge.jpg"
        },
        {
            "title": "How Many Ebola Patients Have Been Treated Outside of Africa?",
            "url": "https://www.nytimes.com/interactive/2014/07/31/world/africa/ebola-virus-outbreak-qa.html",
            "published_date": "2014-08-01T01:14:22+0000",
            "category": "World",
            "abstract": "Questions and answers on the scale of the outbreak and the science of the Ebola virus.",
            "image_url": "https://www.nytimes.com/images/2014/10/01/international-home/ebola-virus-promoimage/ebola-virus-promoimage-articleLarge-v16.png"
        },
        {
            "title": "African Leaders Coming to Talk Business May Also Be Pressed on Rights",
            "url": "https://www.nytimes.com/2014/08/01/us/politics/african-leaders-coming-to-talk-business-may-also-be-pressed-on-rights.html",
            "published_date": "2014-08-01T01:19:04+0000",
            "category": "U.S.",
            "abstract": "The Obama administration said it would seek to build deeper relationships with African leaders, though some advocates worry that human-rights issues will take a back seat.",
            "image_url": null
        },
        {
            "title": "School Shelters in Gaza Offer Limited Safety, and Even Less Comfort",
            "url": "https://www.nytimes.com/2014/08/01/world/middleeast/gaza-school-shelters-offer-limited-safety-and-even-less-comfort.html",
            "published_date": "2014-08-01T01:29:17+0000",
            "category": "World",
            "abstract": "Life for about 200,000 people packed into more than 80 schools serving as shelters in Gaza is full of deprivation and discomfort.",
            "image_url": null
        }
    ],
    "2014-08-02": [
        {
            "title": "A Test for Ukraine in a City Retaken From Rebels",
            "url": "https://www.nytimes.com/2014/08/02/world/europe/a-test-for-ukraine-in-slovyansk-city-retaken-from-pro-russian-rebels.html",
            "published_date": "2014-08-02T00:51:00+0000",
            "category": "World",
            "abstract": "In Slovyansk, a city of 80,000 that was a stronghold for pro-Russian rebels, Ukraine authorities have a difficult task ahead to shift the loyalties of residents to keep the peace.",
            "image_url": "https://www.nytimes.com/images/2014/08/02/world/europe/SLOVYANSK/SLOVYANSK-articleLarge-v2.jpg"
        },
        {
            "title": "Britain Fails to Find Riches It Expected in Swiss Accounts",
            "url": "https://www.nytimes.com/2014/08/02/world/europe/british-authorities-fails-to-find-riches-following-deal-with-swiss-to-crack-down-on-tax-evasion.html",
            "published_date": "2014-08-02T01:06:23+0000",
            "category": "World",
            "abstract": "When the British tax authorities struck a landmark deal with the Swiss to crack down on tax evasion, they sat back and waited for the cash to flow in. Almost three years later, they are still waiting.",
            "image_url": "https://www.nytimes.com/images/2014/08/02/world/HAVENS/HAVENS-articleLarge.jpg"
        },
        {
            "title": "Anti-Semitism Rises in Europe Amid Israel-Gaza Conflict",
            "url": "https://www.nytimes.com/2014/08/02/world/europe/anger-in-europe-over-the-israeli-gaza-conflict-reverberates-as-anti-semitism.html",
            "published_date": "2014-08-02T01:30:28+0000",
            "category": "World",
            "abstract": "Attacks, threats and hate speech have yielded alarm among many Jews and stern language from government leaders.",
            "image_url": "https://www.nytimes.com/images/2014/08/02/world/ANTISEMITISM/ANTISEMITISM-articleLarge.jpg"
        },
        {
            "title": "Birthright Trips to Israel Continue Despite Mideast Conflict",
            "url": "https://www.nytimes.com/2014/08/02/world/middleeast/birthright-trips-to-israel-continue-despite-conflict-between-israel-and-hamas.html",
            "published_date": "2014-08-02T02:06:10+0000",
            "category": "World",
            "abstract": "There have been some cancellations since the hostilities began, but 6,000 young people have visited Israel as planned.",
            "image_url": "https://www.nytimes.com/images/2014/08/02/world/BIRTHRIGHT/BIRTHRIGHT-articleLarge.jpg"
        },
        {
            "title": "North Korea\u2019s Antipathy for the U.S. Is Seen at a New High",
            "url": "https://www.nytimes.com/2014/08/02/world/asia/north-koreas-grievances-for-the-united-states-and-south-korea-is-seen-at-a-new-high.html",
            "published_date": "2014-08-02T02:54:57+0000",
            "category": "World",
            "abstract": "North Korea\u2019s deputy permanent representative, Ri Tong-il, recited grievances with the United States and South Korea, accusing them of conspiring for regime change in the North.",
            "image_url": null
        }
    ],
    "2014-08-03": [
        {
            "title": "Hospitals in Gaza Overwhelmed as Attacks Continue",
            "url": "https://www.nytimes.com/2014/08/03/world/middleeast/hospitals-in-gaza-overcrowded-on-second-day-of-heavy-bombardment-by-israeli-forces.html",
            "published_date": "2014-08-03T01:54:30+0000",
            "category": "World",
            "abstract": "More than 120 Palestinians were killed in Rafah, Gaza Strip, on Friday and Saturday. Those deaths, and hundreds of injuries, overwhelmed the city\u2019s health care facilities.",
            "image_url": "https://www.nytimes.com/images/2014/08/03/world/RAFAH/RAFAH-articleLarge-v2.jpg"
        },
        {
            "title": "Airstrike Near U.N. School Kills 10 as Israel Shifts Troops in Gaza",
            "url": "https://www.nytimes.com/2014/08/04/world/middleeast/israel-gaza-conflict.html",
            "published_date": "2014-08-03T07:38:08+0000",
            "category": "World",
            "abstract": "As Israel began to redeploy significant numbers of troops away from populated areas of Gaza on Sunday, an Israeli Air Force missile struck near the school entrance.",
            "image_url": null
        },
        {
            "title": "1914: Germany Officially Declares War on France",
            "url": "https://iht-retrospective.blogs.nytimes.com/2014/08/03/1914-germany-officially-declares-war-upon-france/",
            "published_date": "2014-08-03T09:29:02+0000",
            "category": "World",
            "abstract": "Highlights from the International Herald Tribune archives: Germany declared war on France in 1914.",
            "image_url": "https://www.nytimes.com/images/2014/08/04/blogs/04iht-oldaug04-BaronVonSchon/04iht-oldaug04-BaronVonSchon-articleLarge.jpg"
        },
        {
            "title": "1939: Woman M.P. Is 1st to Wed in Commons Crypt",
            "url": "https://iht-retrospective.blogs.nytimes.com/2014/08/03/1939-woman-m-p-is-1st-to-wed-in-commons-crypt/",
            "published_date": "2014-08-03T15:24:18+0000",
            "category": "World",
            "abstract": "Highlights from the International Herald Tribune archives: The first wedding of a woman Member of Parliament at Westminster Crypt, in 1939.",
            "image_url": "https://www.nytimes.com/images/2014/08/04/blogs/04iht-oldaug04-ThelmaCazalet/04iht-oldaug04-ThelmaCazalet-jumbo.jpg"
        },
        {
            "title": "China Says Nearly 100 Are Killed in Week of Unrest in Xinjiang",
            "url": "https://www.nytimes.com/2014/08/04/world/asia/china-says-nearly-100-are-killed-in-week-of-unrest-in-xinjiang.html",
            "published_date": "2014-08-03T15:24:39+0000",
            "category": "World",
            "abstract": "The Chinese authorities have characterized the unrest as terrorism, but Uighur advocacy groups have blamed a sweeping security crackdown.",
            "image_url": "https://www.nytimes.com/images/2014/08/03/world/asia/04XINJIANG/04XINJIANG-articleLarge.jpg"
        }
    ],
    "2014-08-04": [
        {
            "title": "Nepal Enthralled by Visit of India Premier, Who Hits \u2018the Right Notes\u2019",
            "url": "https://www.nytimes.com/2014/08/04/world/asia/nepal-enthralled-by-visit-of-indian-prime-minister-narendra-modi-who-hits-the-right-notes.html",
            "published_date": "2014-08-04T00:02:52+0000",
            "category": "World",
            "abstract": "A fractious country, Nepal has been united in its embrace of Narendra Modi, the first Indian prime minister in 17 years to make a state visit here.",
            "image_url": "https://www.nytimes.com/images/2014/08/04/world/NEPAL/NEPAL-articleLarge.jpg"
        },
        {
            "title": "To Evade Russians, Plane Crossed Into Sweden",
            "url": "https://www.nytimes.com/2014/08/04/world/europe/to-evade-russians-american-reconnaissance-plane-crossed-into-swedish-air.html",
            "published_date": "2014-08-04T00:17:30+0000",
            "category": "World",
            "abstract": "An American reconnaissance plane crossed into Swedish air space last month as it sought to avoid being intercepted by Russian fighters, American military officials said.",
            "image_url": null
        },
        {
            "title": "European Sanctions Force Russian Carrier to Suspend Flights",
            "url": "https://www.nytimes.com/2014/08/04/world/europe/european-sanctions-force-russian-carrier-to-suspend-flights.html",
            "published_date": "2014-08-04T00:50:48+0000",
            "category": "World",
            "abstract": "Dobrolet, a low-cost subsidiary of the Russian state carrier Aeroflot, announced that it would suspend all flights as a result of sanctions imposed on Russia by the European Union.",
            "image_url": null
        },
        {
            "title": "A City Divided Over an Occupation Without End",
            "url": "https://www.nytimes.com/2014/08/04/world/europe/independence-square-in-kiev-ukraine-a-city-divided-over-an-occupation-without-end.html",
            "published_date": "2014-08-04T01:21:13+0000",
            "category": "World",
            "abstract": "To some, the barricades in Kiev are an essential reminder of the price Ukrainians paid in blood to protect their freedom, but others want them gone.",
            "image_url": "https://www.nytimes.com/images/2014/08/04/world/KIEV-1/KIEV-1-articleLarge-v2.jpg"
        },
        {
            "title": "Separatist Cadre Hopes for a Reprise in Ukraine",
            "url": "https://www.nytimes.com/2014/08/04/world/europe/separatist-pro-russian-leadership-in-eastern-ukraine-with-a-goal-of-establishing-government.html",
            "published_date": "2014-08-04T01:30:34+0000",
            "category": "World",
            "abstract": "The pro-Russian leadership in eastern Ukraine is pressing ahead with a sweeping goal of establishing a lasting government.",
            "image_url": "https://www.nytimes.com/images/2014/08/04/world/REBELS/REBELS-articleLarge.jpg"
        }
    ],
    "2014-08-05": [
        {
            "title": "Visit From Indian Premier Signals a Political Shift in Nepal",
            "url": "https://www.nytimes.com/2014/08/05/world/asia/visit-from-indian-premier-modi-signals-a-political-shift-in-nepal.html",
            "published_date": "2014-08-05T00:10:47+0000",
            "category": "World",
            "abstract": "Prime Minister Narendra Modi appealed to both politicians and devout Hindus during a recent visit as he announced plans to increase ties between the countries.",
            "image_url": "https://www.nytimes.com/images/2014/08/05/world/05MODI/05MODI-articleLarge.jpg"
        },
        {
            "title": "Ukraine Rebels Conscript \u2018Punishment Brigades\u2019 for Support Work",
            "url": "https://www.nytimes.com/2014/08/05/world/europe/ukraine-rebels-enlisting-punishment-brigades-for-support-work.html",
            "published_date": "2014-08-05T01:13:34+0000",
            "category": "World",
            "abstract": "Glum-looking detainees, often stripped to their underwear, can be seen around Donetsk digging ditches, clearing brush and peeling potatoes.",
            "image_url": "https://www.nytimes.com/images/2014/08/05/world/UKRAINE01/UKRAINE01-articleLarge.jpg"
        },
        {
            "title": "Buildup Makes Russia Battle-Ready for Ukraine",
            "url": "https://www.nytimes.com/2014/08/05/world/europe/buildup-makes-russia-battle-ready-for-ukraine.html",
            "published_date": "2014-08-05T01:43:23+0000",
            "category": "World",
            "abstract": "Adding battalions near the border with Ukraine could allow Russia to launch a cross-border incursion there with little or no warning, Western officials said.",
            "image_url": "https://www.nytimes.com/images/2014/08/05/world/europe/05MILITARY/05MILITARY-articleLarge.jpg"
        },
        {
            "title": "Lax Quarantine Undercuts Ebola Fight in Africa",
            "url": "https://www.nytimes.com/2014/08/05/world/africa/lax-quarantine-undercuts-ebola-fight-in-africa.html",
            "published_date": "2014-08-05T02:26:24+0000",
            "category": "World",
            "abstract": "Sierra Leone, the nation with the most cases of the disease, has banned many public gatherings and set strict quarantine rules, but health officials are deeply worried by loose enforcement efforts.",
            "image_url": "https://www.nytimes.com/images/2014/08/05/world/africa/EBOLA/EBOLA-articleLarge.jpg"
        },
        {
            "title": "Israel Suspends Attack in Parts of Gaza",
            "url": "https://www.nytimes.com/slideshow/2014/08/04/world/middleeast/20140805-ISRAEL-feedss.html",
            "published_date": "2014-08-05T02:39:15+0000",
            "category": "World",
            "abstract": "Minutes after a partial cease-fire was to begin, the Israeli air force struck a refugee camp in Gaza City, killing an 8-year-old and wounding at least 29 others.",
            "image_url": "https://www.nytimes.com/images/2014/08/04/world/middleeast/20140805-ISRAEL-slide-MQVD/20140805-ISRAEL-slide-MQVD-articleLarge.jpg"
        }
    ],
    "2014-08-06": [
        {
            "title": "Vatican Ends Suspension of Nicaraguan Priest",
            "url": "https://www.nytimes.com/2014/08/06/world/americas/vatican-ends-suspension-of-nicaraguan-priest.html",
            "published_date": "2014-08-06T00:52:59+0000",
            "category": "World",
            "abstract": "The Vatican has issued a decree lifting Rev. Miguel F. d\u2019Escoto Brockmann\u2019s suspension after nearly 30 years.",
            "image_url": null
        },
        {
            "title": "Arrest by Israel in Abduction of 3 Youths Is Made Public",
            "url": "https://www.nytimes.com/2014/08/06/world/middleeast/israeli-arrest-made-public-in-abduction-of-3-youths.html",
            "published_date": "2014-08-06T01:13:14+0000",
            "category": "World",
            "abstract": "Israel arrested a Palestinian man last month accused of being the prime mover in the kidnapping and murder of three Israeli teenagers in June, it emerged from court papers.",
            "image_url": null
        },
        {
            "title": "Putin Urges Economic Retaliation for Sanctions Over Ukraine Conflict",
            "url": "https://www.nytimes.com/2014/08/06/world/europe/putin-urges-economic-retaliation-for-sanctions-over-ukraine-conflict.html",
            "published_date": "2014-08-06T01:51:41+0000",
            "category": "World",
            "abstract": "The Russian president said that the measures were necessary to protect manufacturers of consumer goods in his country.",
            "image_url": "https://www.nytimes.com/images/2014/08/06/world/UKRAINE/UKRAINE-articleLarge.jpg"
        },
        {
            "title": "A Part of Hamas Negotiates, and Another May Fight Again",
            "url": "https://www.nytimes.com/2014/08/06/world/middleeast/part-of-hamas-talks-and-part-might-wait-to-fight-again.html",
            "published_date": "2014-08-06T02:11:06+0000",
            "category": "World",
            "abstract": "As Israel and the Palestinians prepared for talks to extend a truce, a senior Hamas leader said the group would keep its political and military wings separate, allowing the latter to prepare for another potential war.",
            "image_url": "https://www.nytimes.com/images/2014/08/06/world/HAMAS/HAMAS-articleLarge.jpg"
        },
        {
            "title": "Catalan Vote Seen as Test for Separatists in Europe",
            "url": "https://www.nytimes.com/2014/08/06/world/europe/catalan-vote-seen-as-test-for-separatists-in-europe.html",
            "published_date": "2014-08-06T02:30:24+0000",
            "category": "World",
            "abstract": "As Catalonia prepares to hold a referendum on independence this fall, concern is growing that the vote could set off a separatist spiral in Spain and other independence-minded regions in Europe.",
            "image_url": "https://www.nytimes.com/images/2014/08/06/world/BASQUE/BASQUE-articleLarge.jpg"
        }
    ],
    "2014-08-07": [
        {
            "title": "Lebanon: Border Standoff Eases",
            "url": "https://www.nytimes.com/2014/08/07/world/middleeast/lebanon-border-standoff-eases.html",
            "published_date": "2014-08-07T00:06:10+0000",
            "category": "World",
            "abstract": "The clashes between the Lebanese Army and Sunni extremist fighters from the Islamic State in Iraq and Syria, who occupied a Lebanese border town last weekend, showed some signs of easing on Wednesday.",
            "image_url": null
        },
        {
            "title": "Islamic Militants in Iraq Are Widely Loathed, Yet Action to Curb Them Is Elusive",
            "url": "https://www.nytimes.com/2014/08/07/world/middleeast/islamic-militants-in-iraq-are-widely-loathed-yet-action-to-curb-them-is-elusive.html",
            "published_date": "2014-08-07T00:46:51+0000",
            "category": "World",
            "abstract": "Any action against the Islamic State in Iraq and Syria is seen as having unintended and potentially harmful consequences.",
            "image_url": null
        },
        {
            "title": "Sunni Extremists Repel Kurdish Forces in Iraq",
            "url": "https://www.nytimes.com/2014/08/07/world/middleeast/sunni-extremists-repel-kurdish-forces-in-iraq.html",
            "published_date": "2014-08-07T00:56:46+0000",
            "category": "World",
            "abstract": "The Islamic State in Iraq and Syria appeared to be making a push along the Kurdish border to take ground, control oil fields and water and expel minority groups.",
            "image_url": "https://www.nytimes.com/images/2014/08/07/world/IRAQ/IRAQ-articleLarge.jpg"
        },
        {
            "title": "Israeli Premier Voices Regret for Civilian Casualties, but Blames Hamas",
            "url": "https://www.nytimes.com/2014/08/07/world/middleeast/israeli-premier-voices-regret-for-civilian-casualties-but-blames-hamas.html",
            "published_date": "2014-08-07T01:09:52+0000",
            "category": "World",
            "abstract": "\u201cEvery civilian casualty is a tragedy, a tragedy of Hamas\u2019s own making,\u201d Prime Minister Benjamin Netanyahu said.",
            "image_url": "https://www.nytimes.com/images/2014/08/07/world/ISRAEL/ISRAEL-articleLarge.jpg"
        },
        {
            "title": "Conflict Leaves Industry in Ashes and Gaza Reeling From Economic Toll",
            "url": "https://www.nytimes.com/2014/08/07/world/middleeast/after-conflict-gaza-industry-lies-in-ashes.html",
            "published_date": "2014-08-07T01:27:26+0000",
            "category": "World",
            "abstract": "In addition to the estimated 1,800 Palestinians killed, business leaders say some 175 industrial plants took devastating blows.",
            "image_url": "https://www.nytimes.com/images/2014/08/07/world/GAZA/GAZA-articleLarge-v2.jpg"
        }
    ],
    "2014-08-08": [
        {
            "title": "Key Cleric in Egypt Rejects Executions",
            "url": "https://www.nytimes.com/2014/08/08/world/middleeast/key-cleric-in-egypt-rejects-executions.html",
            "published_date": "2014-08-08T00:36:40+0000",
            "category": "World",
            "abstract": "In a rare rebuke, Egypt\u2019s highest Muslim religious authority refused to approve court-ordered death sentences on leaders of the Muslim Brotherhood, court officials said.",
            "image_url": "https://www.nytimes.com/images/2014/08/08/world/EGYPT/EGYPT-articleLarge.jpg"
        },
        {
            "title": "In Peru, Trading Boats for Boards",
            "url": "https://www.nytimes.com/video/world/americas/100000003042141/in-peru-trading-boats-for-boards.html",
            "published_date": "2014-08-08T01:06:11+0000",
            "category": "World",
            "abstract": "On Peru\u2019s northern coastline, the long history of reedboats is threatened as a new generation looks beyond fishing for careers and opportunities like surfing.",
            "image_url": "https://www.nytimes.com/images/2014/08/06/multimedia/peru-reed-boat-surfer/peru-reed-boat-surfer-articleLarge.jpg"
        },
        {
            "title": "Uighurs\u2019 Veils Signal Protest Against China\u2019s Restrictions",
            "url": "https://www.nytimes.com/2014/08/08/world/asia/uighurs-veils-a-protest-against-chinas-curbs.html",
            "published_date": "2014-08-08T01:27:52+0000",
            "category": "World",
            "abstract": "The Chinese authorities have cast a net over a wide range of Uighur practices, including veils and long beards, seen as signs of religious extremism.",
            "image_url": null
        },
        {
            "title": "Israeli Procedure Reignites Old Debate",
            "url": "https://www.nytimes.com/2014/08/08/world/middleeast/israeli-procedure-reignites-old-debate.html",
            "published_date": "2014-08-08T02:29:40+0000",
            "category": "World",
            "abstract": "The Israeli military\u2019s \u201cHannibal procedure\u201d is intended to prevent captors from getting away with their captives, even at the risk of endangering the lives of the captured Israeli soldiers.",
            "image_url": "https://www.nytimes.com/images/2014/08/07/world/GAZASTRIP-1407452999942/ISRAEL-1407452999942-articleLarge.jpg"
        },
        {
            "title": "Town\u2019s Floating Symbol Fading Into the Sunset",
            "url": "https://www.nytimes.com/2014/08/08/world/americas/towns-floating-symbol-fading-into-the-sunset.html",
            "published_date": "2014-08-08T02:31:20+0000",
            "category": "World",
            "abstract": "Small boats made of reeds have been used for hundreds of years in a Peruvian village, but the reed beds are dwindling and so is interest in the fishing life the boats make possible.",
            "image_url": null
        }
    ],
    "2014-08-09": [
        {
            "title": "Half a Ton of This, Half a Ton of That: Russia Is Calm Over Food Import Bans",
            "url": "https://www.nytimes.com/2014/08/09/world/europe/half-a-ton-of-this-half-a-ton-of-that-russia-calm-over-food-import-bans.html",
            "published_date": "2014-08-09T00:30:57+0000",
            "category": "World",
            "abstract": "Retaliatory sanctions against Western products have led to a \u201cbuy Russian\u201d campaign and some signs that there were ways around the problem.",
            "image_url": "https://www.nytimes.com/images/2014/08/09/world/RUSSIA-1/RUSSIA-1-articleLarge.jpg"
        },
        {
            "title": "Motorbikers in North Korea Are Told to Park to Save Fuel",
            "url": "https://www.nytimes.com/2014/08/09/world/asia/motorbikers-in-north-korea-are-told-to-park-to-save-fuel.html",
            "published_date": "2014-08-09T00:52:28+0000",
            "category": "World",
            "abstract": "Motorbike use by ordinary citizens has been cut to rush hours to ensure fuel for the government and the military personnel, two websites that monitor North Korea said, adding that a decline in Chinese oil imports was probably responsible.",
            "image_url": null
        },
        {
            "title": "Turkey Votes for a President",
            "url": "https://www.nytimes.com/slideshow/2014/08/09/world/europe/20140809-TURKEY.html",
            "published_date": "2014-08-09T01:20:15+0000",
            "category": "World",
            "abstract": "Prime Minister Recep Tayyip Erdogan Erdogan is considered the leading candidate as Turkey conducts its first direct election for president.",
            "image_url": "https://www.nytimes.com/images/2014/08/09/world/20140809-TURKEY-slide-23AN/20140809-TURKEY-slide-23AN-articleLarge.jpg"
        },
        {
            "title": "Turkey\u2019s Premier Tries to Keep Power, as President",
            "url": "https://www.nytimes.com/2014/08/09/world/europe/premier-tries-to-keep-power-as-president.html",
            "published_date": "2014-08-09T01:21:33+0000",
            "category": "World",
            "abstract": "Prime Minister Recep Tayyip Erdogan is expected to win Sunday\u2019s presidential vote and transform an office that has been largely ceremonial.",
            "image_url": null
        },
        {
            "title": "Differences Between Israel and U.N. Over Gaza Episodes Go Back Years",
            "url": "https://www.nytimes.com/2014/08/09/world/middleeast/differences-between-israel-and-un-over-gaza-episodes-go-back-years.html",
            "published_date": "2014-08-09T02:11:32+0000",
            "category": "World",
            "abstract": "Israeli attacks on United Nations facilities are repeating a pattern that an agency board of inquiry reported in 2009. Israel says it is addressing the issues.",
            "image_url": null
        }
    ],
    "2014-08-10": [
        {
            "title": "44 Dead in Tour Bus Crash in Tibet",
            "url": "https://www.nytimes.com/2014/08/11/world/asia/tour-bus-crash-in-tibet.html",
            "published_date": "2014-08-10T10:16:45+0000",
            "category": "World",
            "abstract": "A bus carrying about 50 passengers crashed into two vehicles and fell 30 feet off a mountainous highway on Saturday, the state news media said.",
            "image_url": "https://www.nytimes.com/images/2014/08/10/world/asia/11TIBET/11TIBET-articleLarge.jpg"
        },
        {
            "title": "Kerry Urges Myanmar to Stay on Path to Democracy, Despite Stumbles",
            "url": "https://www.nytimes.com/2014/08/11/world/asia/kerry-citing-bumps-urges-myanmar-to-stay-on-path-to-democracy.html",
            "published_date": "2014-08-10T13:39:43+0000",
            "category": "World",
            "abstract": "Secretary of State John Kerry, on the final day of a trip to Myanmar, pushed for further progress in what many perceive to be slowing political and legal overhauls.",
            "image_url": "https://www.nytimes.com/images/2014/08/11/world/DIPLO/DIPLO-articleLarge.jpg"
        },
        {
            "title": "Agreeing to More Talks in Egypt, Israelis and Palestinians Begin Latest Cease-Fire",
            "url": "https://www.nytimes.com/2014/08/11/world/middleeast/israel-gaza-strip-conflict.html",
            "published_date": "2014-08-10T14:07:38+0000",
            "category": "World",
            "abstract": "The new truce began at 12:01 a.m. Monday, after both sides agreed to a resumption of Egyptian-mediated negotiations toward a more durable solution.",
            "image_url": "https://www.nytimes.com/images/2014/08/11/world/ISRAEL/ISRAEL-articleLarge.jpg"
        },
        {
            "title": "Capitalizing on U.S. Bombing, Kurds Retake Iraqi Towns",
            "url": "https://www.nytimes.com/2014/08/11/world/middleeast/iraq.html",
            "published_date": "2014-08-10T14:36:14+0000",
            "category": "World",
            "abstract": "As Kurdish officials said they were making advances against Sunni militants, Iraq's political crisis deepened, with a deadline expiring for the president to choose a nominee for prime minister.",
            "image_url": "https://www.nytimes.com/images/2014/08/11/world/11IRAQ-1/11IRAQ-1-articleLarge-v2.jpg"
        },
        {
            "title": "1939: U.S. Zionist Delegation to Geneva in Quest of Solution to Palestine",
            "url": "https://iht-retrospective.blogs.nytimes.com/2014/08/10/1939-u-s-zionist-delegation-to-geneva-in-quest-of-solution-to-palestine/",
            "published_date": "2014-08-10T14:37:56+0000",
            "category": "World",
            "abstract": "From the International Herald Tribune archives: An American delegation travels to the World Zionist Congress in 1939.",
            "image_url": "https://www.nytimes.com/images/2014/08/11/blogs/11iht-oldaug11/11iht-oldaug11-articleLarge.png"
        }
    ],
    "2014-08-11": [
        {
            "title": "Taliban Take Responsibility for Bombing in Kabul",
            "url": "https://www.nytimes.com/2014/08/11/world/asia/taliban-take-responsibility-for-bombing-in-kabul.html",
            "published_date": "2014-08-11T00:13:02+0000",
            "category": "World",
            "abstract": "While they have repeatedly fired rockets at the airport and carried out a broad campaign of violence across the country, the suicide attacks that have been a hallmark of the war have been less common in the capital.",
            "image_url": null
        },
        {
            "title": "Ebola May Pose Little Threat to U.S., but It Looms Large on Twitter",
            "url": "https://www.nytimes.com/2014/08/11/world/ebola-may-pose-little-threat-to-us-but-it-looms-large-on-twitter.html",
            "published_date": "2014-08-11T00:54:05+0000",
            "category": "World",
            "abstract": "It is the vividness of a perceived threat, rather than the threat\u2019s true potency, that plays the bigger role in the potential to spread through social media, researchers find.",
            "image_url": null
        },
        {
            "title": "Scrambling Down an Iraqi Mountain, Yazidi Families Search for Missing",
            "url": "https://www.nytimes.com/2014/08/11/world/middleeast/scrambling-down-an-iraqi-mountain-yazidi-families-search-for-missing.html",
            "published_date": "2014-08-11T01:34:37+0000",
            "category": "World",
            "abstract": "Many Yazidis who had fled the advance of ISIS militants have become separated from their families, some in their flight to the mountains, and some when they made the decision to come down.",
            "image_url": "https://www.nytimes.com/images/2014/08/11/world/SINJAR-1/SINJAR-1-articleLarge.jpg"
        },
        {
            "title": "Renewed Shelling in Donetsk",
            "url": "https://www.nytimes.com/slideshow/2014/08/10/world/europe/20140811-ukraine-feeds.html",
            "published_date": "2014-08-11T02:05:19+0000",
            "category": "World",
            "abstract": "Artillery pounded Donetsk, Ukraine, on Sunday as the West warned Russia that any attempt to send \u201chumanitarian\u201d troops into the region would be deemed \u201cunacceptable.\u201d",
            "image_url": "https://www.nytimes.com/images/2014/08/10/world/europe/20140811-ukraine-slide-9YHO/20140811-ukraine-slide-9YHO-articleLarge.jpg"
        },
        {
            "title": "In Gaza, Grief, Anger \u2014 and No Small Measure of Pride",
            "url": "https://www.nytimes.com/2014/08/11/world/middleeast/gaza-strip-palestinians-are-exhausted-but-hold-on-to-hope-war-brings-change.html",
            "published_date": "2014-08-11T02:12:11+0000",
            "category": "World",
            "abstract": "In interviews across Gaza, many Palestinians insisted they could withstand much more to achieve their goals of opening borders and removing Israeli restrictions on imports and exports.",
            "image_url": "https://www.nytimes.com/images/2014/08/11/world/GAZA/GAZA-articleLarge.jpg"
        }
    ],
    "2014-08-12": [
        {
            "title": "Killings Rise in Karachi as Taliban Target Police",
            "url": "https://www.nytimes.com/2014/08/12/world/asia/killings-rise-in-karachi-as-taliban-target-police.html",
            "published_date": "2014-08-12T00:06:19+0000",
            "category": "World",
            "abstract": "In the Pashtun slums of Karachi, Pakistan, militants have gunned down police officers, assaulted poorly defended police stations and dispatched suicide bombers to assassinate top police commanders.",
            "image_url": null
        },
        {
            "title": "Standing Guard Over a Monarchy\u2019s Tainted Legacy",
            "url": "https://www.nytimes.com/2014/08/12/world/europe/standing-guard-over-a-monarchys-tainted-legacy.html",
            "published_date": "2014-08-12T00:23:15+0000",
            "category": "World",
            "abstract": "The guards at the massive mausoleums commemorating Italy\u2019s former monarchs struggle to preserve respect for those who once united the country.",
            "image_url": "https://www.nytimes.com/images/2014/08/12/world/12ROME/12ROME-articleLarge.jpg"
        },
        {
            "title": "For 2 U.S. Presidents, Iraqi Leader Proved a Source of Frustration",
            "url": "https://www.nytimes.com/2014/08/12/world/middleeast/for-2-us-presidents-iraqi-leader-proved-a-source-of-frustration.html",
            "published_date": "2014-08-12T00:54:54+0000",
            "category": "World",
            "abstract": "Nuri Kamal al-Maliki rose from obscurity to power in part with American help, but U.S. leaders found him an often unconstructive ally who caused as many headaches as he solved.",
            "image_url": "https://www.nytimes.com/images/2014/08/12/world/middleeast/12MALIKI1/12MALIKI1-articleLarge.jpg"
        },
        {
            "title": "At Heart of Ebola Outbreak, a Village Frozen by Fear and Death",
            "url": "https://www.nytimes.com/2014/08/12/world/africa/at-heart-of-ebola-outbreak-a-village-frozen-by-fear-and-death.html",
            "published_date": "2014-08-12T01:16:35+0000",
            "category": "World",
            "abstract": "More than 60 people have died from the virus in a tiny village in Sierra Leone, and now people there worry that a quarantine will cut off their food and supplies.",
            "image_url": null
        },
        {
            "title": "Pentagon Says Airstrikes Have Slowed but Not Stopped Sunni Militants",
            "url": "https://www.nytimes.com/2014/08/12/world/middleeast/pentagon-says-airstrikes-have-slowed-but-not-stopped-sunni-militants.html",
            "published_date": "2014-08-12T01:41:23+0000",
            "category": "World",
            "abstract": "Airstrikes have slowed the progress of Sunni militants laying siege to refugees on Mount Sinjar, but Pentagon officials also said that ISIS remained on the offense.",
            "image_url": "https://www.nytimes.com/images/2014/08/12/world/MILITARY-1/MILITARY-1-articleLarge.jpg"
        }
    ],
    "2014-08-13": [
        {
            "title": "Why Obama Is Helping the Yazidis in Iraq",
            "url": "https://www.nytimes.com/video/world/100000003052718/why-obama-helped-the-yazidis-in-iraq.html",
            "published_date": "2014-08-13T00:12:04+0000",
            "category": "World",
            "abstract": "With humanitarian crises around the world, a look at why President Obama decided to use military force to help the Yazidis, a religious minority in Iraq.",
            "image_url": "https://www.nytimes.com/images/2014/08/12/multimedia/yazidis-explainer/yazidis-explainer-articleLarge.jpg"
        },
        {
            "title": "In Increase, U.S. to Send 130 Advisers to Aid Iraqis",
            "url": "https://www.nytimes.com/2014/08/13/world/middleeast/us-to-send-130-more-military-advisers-to-iraq.html",
            "published_date": "2014-08-13T00:15:14+0000",
            "category": "World",
            "abstract": "The additional advisers will aid in the rescue of displaced people trapped by jihadists on Mount Sinjar, Defense Department officials said.",
            "image_url": "https://www.nytimes.com/images/2014/08/14/world/12MILITARY/12MILITARY-articleLarge.jpg"
        },
        {
            "title": "In Pope\u2019s Trip to South Korea, Church Envisions Growth",
            "url": "https://www.nytimes.com/2014/08/13/world/asia/pontiffs-trip-to-south-korea-reflects-hopes-to-expand.html",
            "published_date": "2014-08-13T02:14:32+0000",
            "category": "World",
            "abstract": "During the first visit by a pontiff since 1989, Pope Francis will preach to laid-off workers and the country will witness a beatification.",
            "image_url": "https://www.nytimes.com/images/2014/08/13/world/POPE/POPE-articleLarge-v2.jpg"
        },
        {
            "title": "Indian Premier Denounces Pakistan for \u2018Proxy War\u2019",
            "url": "https://www.nytimes.com/2014/08/13/world/asia/indian-premier-denounces-pakistan-for-proxy-war.html",
            "published_date": "2014-08-13T02:24:00+0000",
            "category": "World",
            "abstract": "On a visit to Kashmir, Narendra Modi condemned his neighbor as cease-fire violations rise in the border area.",
            "image_url": null
        },
        {
            "title": "Using a Tactic Unseen in a Century, Countries Cordon Off Ebola-Racked Areas",
            "url": "https://www.nytimes.com/2014/08/13/science/using-a-tactic-unseen-in-a-century-countries-cordon-off-ebola-racked-areas.html",
            "published_date": "2014-08-13T02:28:14+0000",
            "category": "Science",
            "abstract": "A \u201ccordon sanitaire,\u201d a tactic more common in the medieval era, is being carried out in Guinea, Sierra Leone and Liberia, but it has the potential to become inhumane.",
            "image_url": null
        }
    ],
    "2014-08-14": [
        {
            "title": "Plane Crash Kills Brazilian Politician",
            "url": "https://www.nytimes.com/video/world/americas/100000003054173/plane-crash-kills-brazilian-politician.html",
            "published_date": "2014-08-14T00:34:27+0000",
            "category": "World",
            "abstract": "Television footage of the immediate aftermath of a plane crash in a residential area that killed the Brazilian presidential candidate Eduardo Campos and six others.",
            "image_url": "https://www.nytimes.com/images/2014/08/13/multimedia/brazil-plane-crash/brazil-plane-crash-articleLarge.jpg"
        },
        {
            "title": "Brazilian Presidential Candidate Dies in Plane Crash, Upsetting Race",
            "url": "https://www.nytimes.com/2014/08/14/world/americas/brazilian-presidential-candidate-dies-in-plane-crash-upsetting-race.html",
            "published_date": "2014-08-14T00:36:52+0000",
            "category": "World",
            "abstract": "Eduardo Campos\u2019s unexpected death leaves his supporters up for grabs for the leading candidates, as well as his running mate, who may take his place.",
            "image_url": "https://www.nytimes.com/images/2014/08/14/world/BRAZIL/BRAZIL-articleLarge.jpg"
        },
        {
            "title": "Rocket Fire Casts Doubt on Truce in Gaza",
            "url": "https://www.nytimes.com/2014/08/14/world/middleeast/rocket-fire-casts-doubt-on-truce-in-gaza.html",
            "published_date": "2014-08-14T00:49:17+0000",
            "category": "World",
            "abstract": "The new exchanges between Israel and elements in Gaza marred an agreement to extend a cease-fire for another five days.",
            "image_url": "https://www.nytimes.com/images/2014/08/15/world/14gaza/14gaza-articleLarge.jpg"
        },
        {
            "title": "Saudis Give $100 Million to U.N. Fight on Terrorism",
            "url": "https://www.nytimes.com/2014/08/14/world/middleeast/saudis-give-100-million-to-un-fight-on-terrorism.html",
            "published_date": "2014-08-14T01:06:36+0000",
            "category": "World",
            "abstract": "A large gift to the United Nations Counter-Terrorism Center as Islamist militant extremism hits ever closer to home.",
            "image_url": null
        },
        {
            "title": "For U.N. Leader on Human Rights, Finish Line Looks Blurry",
            "url": "https://www.nytimes.com/2014/08/14/world/europe/for-un-leader-on-human-rights-finish-line-looks-blurry.html",
            "published_date": "2014-08-14T01:24:17+0000",
            "category": "World",
            "abstract": "Known for her bluntness, Navi Pillay held the post of United Nations high commissioner for human rights longer than any of her predecessors.",
            "image_url": "https://www.nytimes.com/images/2014/08/14/world/PILLAY/PILLAY-articleLarge.jpg"
        }
    ],
    "2014-08-15": [
        {
            "title": "Maliki Steps Aside in Iraq",
            "url": "https://www.nytimes.com/video/world/middleeast/100000003057014/maliki-steps-aside-in-iraq.html",
            "published_date": "2014-08-15T00:01:18+0000",
            "category": "World",
            "abstract": "Prime Minister Nuri Kamal al-Maliki of Iraq agreed to end his legal challenge to the nomination of his replacement, Haider al-Abadi.",
            "image_url": "https://www.nytimes.com/images/2014/08/14/multimedia/maliki-steps-down/maliki-steps-down-articleLarge-v2.jpg"
        },
        {
            "title": "In Nepal, a Better Life With a Steep Price",
            "url": "https://www.nytimes.com/2014/08/15/world/asia/in-nepal-a-better-life-with-a-steep-price.html",
            "published_date": "2014-08-15T00:37:42+0000",
            "category": "World",
            "abstract": "Plagued by endemic poverty, many young people in Nepal leave to work abroad. But the backbreaking labor they find there often results in death.",
            "image_url": "https://www.nytimes.com/images/2014/08/15/world/15NEPAL/15NEPAL-articleLarge-v2.jpg"
        },
        {
            "title": "A Ukrainian City Under Siege",
            "url": "https://www.nytimes.com/slideshow/2014/08/15/world/europe/20140815-LUHANSK.html",
            "published_date": "2014-08-15T01:20:46+0000",
            "category": "World",
            "abstract": "Luhansk is a grim place, but for residents, shelling remains the greatest danger and the most trying aspect of daily life.",
            "image_url": "https://www.nytimes.com/images/2014/08/15/world/20140815-LUHANSK-slide-VFV6/20140815-LUHANSK-slide-VFV6-articleLarge.jpg"
        },
        {
            "title": "A Ukraine City Under Siege, \u2018Just Terrified of the Bombing\u2019",
            "url": "https://www.nytimes.com/2014/08/15/world/europe/a-ukraine-city-under-siege-just-terrified-of-the-bombing.html",
            "published_date": "2014-08-15T01:21:06+0000",
            "category": "World",
            "abstract": "Life in Luhansk, Ukraine, is tough, but far from catastrophic. The only relief most people here seek is from the shelling, which goes on night and day.",
            "image_url": null
        },
        {
            "title": "U.S. Pulls Back on Plans for a Mountain Rescue",
            "url": "https://www.nytimes.com/2014/08/15/world/middleeast/joy-in-us-at-news-that-yazidi-plight-is-easing.html",
            "published_date": "2014-08-15T01:39:49+0000",
            "category": "World",
            "abstract": "Far fewer refugees were discovered on a mountain in Iraq, a U.S. team reported, and they were no longer either starving or stranded.",
            "image_url": "https://www.nytimes.com/images/2014/08/15/world/MILITARY/MILITARY-articleLarge.jpg"
        }
    ],
    "2014-08-16": [
        {
            "title": "Witness in War Crimes Court Tallies Cost of a Decade in Hiding",
            "url": "https://www.nytimes.com/2014/08/16/world/europe/war-crimes-yugoslavia-serbia-slobodan-milosevic-hague.html",
            "published_date": "2014-08-16T00:06:15+0000",
            "category": "World",
            "abstract": "When a young woman from Belgrade volunteered to testify in a case involving Slobodan Milosevic, she was promised protection. Today she says her life is ruined.",
            "image_url": "https://www.nytimes.com/images/2014/08/17/world/16witness-new/16witness-new-articleLarge.jpg"
        },
        {
            "title": "Spain Suspects Morocco Allowed a Brief Flood of Migrants",
            "url": "https://www.nytimes.com/2014/08/16/world/europe/spain-suspects-morocco-allowed-a-brief-flood-of-migrants.html",
            "published_date": "2014-08-16T00:41:46+0000",
            "category": "World",
            "abstract": "Spanish analysts believe that the influx of Africans to Spain\u2019s borders was orchestrated by its neighbor across the Strait of Gibraltar.",
            "image_url": "https://www.nytimes.com/images/2014/08/16/world/16SPAIN/16SPAIN-articleLarge.jpg"
        },
        {
            "title": "In an Iraqi Town Hollowed Out by Jihadists, There Is No Going Back to How It Was",
            "url": "https://www.nytimes.com/2014/08/16/world/middleeast/in-an-Iraqi-town-hollowed-out-by-jihadists-there-is-no-going-back-to-how-it-was.html",
            "published_date": "2014-08-16T01:19:40+0000",
            "category": "World",
            "abstract": "Nearly a week after American airstrikes paved the way for Kurdish forces to reclaim Mahmour from the Sunni militants of ISIS, very few people have returned.",
            "image_url": null
        },
        {
            "title": "Robert Richards, Marine Guilty in Taliban Desecration, Dies at 28",
            "url": "https://www.nytimes.com/2014/08/16/world/robert-richards-marine-guilty-in-taliban-desecration-dies-at-28.html",
            "published_date": "2014-08-16T01:35:32+0000",
            "category": "World",
            "abstract": "Mr. Richards was a sergeant who was demoted after video footage surfaced of him and his colleagues urinating on corpses of Taliban fighters in Afghanistan.",
            "image_url": null
        },
        {
            "title": "As World Boils, Fingers Point Obama\u2019s Way",
            "url": "https://www.nytimes.com/2014/08/16/world/middleeast/as-world-boils-fingers-point-obamas-way.html",
            "published_date": "2014-08-16T01:42:01+0000",
            "category": "World",
            "abstract": "Buffeted by international instability, the president stresses that there are limits to American power, and that the chief executive is not omnipotent.",
            "image_url": null
        }
    ],
    "2014-08-17": [
        {
            "title": "Battling Ebola in Liberia",
            "url": "https://www.nytimes.com/slideshow/2014/08/16/world/africa/17ebola-ss-now.html",
            "published_date": "2014-08-17T02:27:01+0000",
            "category": "World",
            "abstract": "Efforts to identify and quarantine people infected with Ebola in the poor West Point neighborhood of Monrovia have been haphazard, chaotic and largely ineffective.",
            "image_url": "https://www.nytimes.com/images/2014/08/16/world/africa/17ebola-hp-slide-4D9P/17ebola-hp-slide-4D9P-articleLarge.jpg"
        },
        {
            "title": "Transplant Brokers in Israel Lure Desperate Kidney Patients to Costa Rica",
            "url": "https://www.nytimes.com/2014/08/17/world/middleeast/transplant-brokers-in-israel-lure-desperate-kidney-patients-to-costa-rica.html",
            "published_date": "2014-08-17T06:04:01+0000",
            "category": "World",
            "abstract": "Facing the prospect of impossibly long waiting lists for organs, some patients have turned to an underground trade that pairs them with people willing to sell an organ.",
            "image_url": "https://www.nytimes.com/images/2014/08/17/world/17organs-ophira/17organs-ophira-articleLarge.jpg"
        },
        {
            "title": "An Impossible Wait List",
            "url": "https://www.nytimes.com/video/world/middleeast/100000003054302/an-impossible-wait-list.html",
            "published_date": "2014-08-17T06:07:45+0000",
            "category": "World",
            "abstract": "Amos Canaf, founder of an advocacy group for renal patients, argues that the kidney shortage leaves patients with few choices other than to go overseas for a transplant.",
            "image_url": "https://www.nytimes.com/images/2014/08/13/multimedia/inv-organs-canaf/inv-organs-canaf-articleLarge.jpg"
        },
        {
            "title": "Advocate for Deceased Organ Donation",
            "url": "https://www.nytimes.com/video/world/middleeast/100000003054224/advocate-for-deceased-organ-donations.html",
            "published_date": "2014-08-17T06:07:45+0000",
            "category": "World",
            "abstract": "Rabbi Shlomo Amar believes that recovering an organ from someone who is brain dead does not violate Jewish law.",
            "image_url": "https://www.nytimes.com/images/2014/08/13/multimedia/inv-organs/inv-organs-articleLarge.jpg"
        },
        {
            "title": "Opposes Deceased Organ Donations",
            "url": "https://www.nytimes.com/video/world/middleeast/100000003057926/opposes-deceased-organ-donations.html",
            "published_date": "2014-08-17T06:07:48+0000",
            "category": "World",
            "abstract": "Rabbi Yeshayahu Heber set up an organization to promote living donation amongst Orthodox Jews but believes that organ donation by the brain dead violates Jewish law.",
            "image_url": "https://www.nytimes.com/images/2014/08/15/multimedia/inv-organs-heber/inv-organs-heber-articleLarge.jpg"
        }
    ],
    "2014-08-18": [
        {
            "title": "Case in Which Abortion Was Denied Reignites Controversy Over Irish Law",
            "url": "https://www.nytimes.com/2014/08/18/world/europe/case-in-which-abortion-was-denied-reignites-controversy-over-irish-law.html",
            "published_date": "2014-08-18T00:19:35+0000",
            "category": "World",
            "abstract": "The woman, who is not an Irish citizen, sought an abortion under a clause in the new Protection of Life During Pregnancy Act, saying that she was suicidal.",
            "image_url": null
        },
        {
            "title": "The Chasm Tilting Scots Toward Independence",
            "url": "https://www.nytimes.com/2014/08/18/world/europe/the-chasm-tilting-scots-toward-independence.html",
            "published_date": "2014-08-18T01:02:47+0000",
            "category": "World",
            "abstract": "Conservatives\u2019 sway has dwindled in the north, and some left-leaning Scots are thinking of going their own way.",
            "image_url": "https://www.nytimes.com/images/2014/08/18/world/SCOTTISH-1/SCOTTISH-1-articleLarge.jpg"
        },
        {
            "title": "The Displaced in Gaza",
            "url": "https://www.nytimes.com/slideshow/2014/08/18/world/middleeast/20140818-GAZA.html",
            "published_date": "2014-08-18T01:14:50+0000",
            "category": "World",
            "abstract": "With 11,000 homes destroyed and many more damaged, a humanitarian crisis is just beginning.",
            "image_url": "https://www.nytimes.com/images/2014/08/18/world/20140818-GAZA-slide-NYJP/20140818-GAZA-slide-NYJP-articleLarge.jpg"
        },
        {
            "title": "In Torn Gaza, if Roof Stands, It\u2019s Now Home",
            "url": "https://www.nytimes.com/2014/08/18/world/middleeast/gaza-strip-war-leaves-another-crisis-for-displaced-gazans.html",
            "published_date": "2014-08-18T01:14:54+0000",
            "category": "World",
            "abstract": "With an estimated 11,000 homes destroyed and many more severely damaged, Gaza\u2019s housing and humanitarian troubles are just beginning.",
            "image_url": "https://www.nytimes.com/images/2014/08/18/world/middleeast/GAZA/GAZA-articleLarge.jpg"
        },
        {
            "title": "For Chinese, Pope Seems Worlds Away in South Korea",
            "url": "https://www.nytimes.com/2014/08/18/world/asia/for-chinese-pope-seems-worlds-away-in-south-korea.html",
            "published_date": "2014-08-18T01:48:06+0000",
            "category": "World",
            "abstract": "The sparse news treatment of the pope\u2019s first visit to the Far East is indicative of the Chinese Communist Party\u2019s continuing attempts to maintain a tight grip on Catholicism.",
            "image_url": "https://www.nytimes.com/images/2014/08/18/world/CATHOLICS-2/CATHOLICS-2-articleLarge-v3.jpg"
        }
    ],
    "2014-08-19": [
        {
            "title": "Attacks on Aid Workers Jump Worldwide, Group Says",
            "url": "https://www.nytimes.com/2014/08/19/world/asia/attacks-on-aid-workers-jump-worldwide-group-says.html",
            "published_date": "2014-08-19T00:15:50+0000",
            "category": "World",
            "abstract": "The sharp rise over the past year and a half reflects a surge in conflict zones.",
            "image_url": null
        },
        {
            "title": "Airstrikes Over Tripoli Kill Six; Source of Bombing Is Unknown",
            "url": "https://www.nytimes.com/2014/08/19/world/africa/airstrikes-over-tripoli-kill-six-source-of-bombing-is-unknown.html",
            "published_date": "2014-08-19T00:27:57+0000",
            "category": "World",
            "abstract": "The warplanes struck targets controlled by Islamists, and Libyan authorities attributed the attacks to a foreign state.",
            "image_url": null
        },
        {
            "title": "Surviving Ebola, but Untouchable Back Home",
            "url": "https://www.nytimes.com/2014/08/19/world/africa/surviving-ebola-but-untouchable-back-home.html",
            "published_date": "2014-08-19T01:04:41+0000",
            "category": "World",
            "abstract": "As some survivors come back to the world of the living, they feel a chill of wariness, or worse, from neighbors.",
            "image_url": "https://www.nytimes.com/images/2014/08/19/world/africa/SIERRA/SIERRA-articleLarge-v3.jpg"
        },
        {
            "title": "Amid Election Impasse, Calls in Afghanistan for an Interim Government",
            "url": "https://www.nytimes.com/2014/08/19/world/asia/amid-election-impasse-calls-in-afghanistan-for-an-interim-government.html",
            "published_date": "2014-08-19T01:08:49+0000",
            "category": "World",
            "abstract": "Several top officials in the government say a ruling committee might be best for now as the candidates in Afghanistan\u2019s recent presidential vote dispute the results.",
            "image_url": "https://www.nytimes.com/images/2014/08/19/world/INTERIM/INTERIM-articleLarge-v3.jpg"
        },
        {
            "title": "In China, Myths of Social Cohesion",
            "url": "https://www.nytimes.com/2014/08/19/world/asia/in-china-myths-of-social-cohesion.html",
            "published_date": "2014-08-19T01:26:58+0000",
            "category": "World",
            "abstract": "China\u2019s Communist Party has devoted enormous resources to composing historical narratives, like that of the Fragrant Concubine, that seek to legitimize its rule.",
            "image_url": "https://www.nytimes.com/images/2014/08/19/world/KASHGAR/KASHGAR-articleLarge.jpg"
        }
    ],
    "2014-08-20": [
        {
            "title": "Saudi Prince Is Identified as Target of Paris Heist",
            "url": "https://www.nytimes.com/2014/08/20/world/europe/saudi-prince-is-identified-as-target-of-paris-heist.html",
            "published_date": "2014-08-20T00:13:33+0000",
            "category": "World",
            "abstract": "While the police in France have refused to release his identity, the French news media reported that it was Prince Abdul Aziz, 41, who was ambushed by gunmen in a Hollywood-style robbery.",
            "image_url": "https://www.nytimes.com/images/2014/08/20/world/PARIS/PARIS-articleLarge.jpg"
        },
        {
            "title": "Plenty of Room at the Top of Ukraine\u2019s Fading Rebellion",
            "url": "https://www.nytimes.com/2014/08/20/world/europe/plenty-of-room-at-the-top-of-ukraines-fading-rebellion.html",
            "published_date": "2014-08-20T00:35:56+0000",
            "category": "World",
            "abstract": "In what separatist officials call the \u201cUkrainianization\u201d of the leadership, almost all the original Russian leaders of the rebellion have resigned and gone home, replaced by Ukrainians of dubious qualifications.",
            "image_url": "https://www.nytimes.com/images/2014/08/20/world/ALT-REBELS/ALT-REBELS-articleLarge-v3.jpg"
        },
        {
            "title": "A Trove of Diaries Meant to Be Read by Others",
            "url": "https://www.nytimes.com/2014/08/20/world/europe/a-trove-of-diaries-meant-to-be-read-by-others.html",
            "published_date": "2014-08-20T00:57:11+0000",
            "category": "World",
            "abstract": "Having collected more than 7,000 personal memoirs, Italy\u2019s Pieve Santo Stefano has become known as the City of Diaries.",
            "image_url": "https://www.nytimes.com/images/2014/08/20/world/ARCHIVE/ARCHIVE-articleLarge.jpg"
        },
        {
            "title": "German Leader Emerges as Key Figure in Ukraine Talks",
            "url": "https://www.nytimes.com/2014/08/20/world/europe/german-leader-emerges-as-key-figure-in-ukraine-talks.html",
            "published_date": "2014-08-20T01:06:26+0000",
            "category": "World",
            "abstract": "Chancellor Angela Merkel of Germany is emerging more and more as a pivotal leader on the Ukraine conflict as she dances delicately between opposing forces.",
            "image_url": "https://www.nytimes.com/images/2014/08/20/world/20Merkel/20Merkel-articleLarge.jpg"
        },
        {
            "title": "Russia, Iran and Egypt Heckle U.S. About Tactics in Ferguson",
            "url": "https://www.nytimes.com/2014/08/20/world/europe/russia-iran-and-egypt-heckle-us-about-tactics-in-ferguson.html",
            "published_date": "2014-08-20T01:23:53+0000",
            "category": "World",
            "abstract": "Strident criticism of the action taken by the police in Ferguson, Mo., has come from authoritarian nations where the police are often venerated and dissent is scarcely tolerated.",
            "image_url": "https://www.nytimes.com/images/2014/08/19/world/europe/19open_rt/19open_rt-articleLarge.jpg"
        }
    ],
    "2014-08-21": [
        {
            "title": "Rifts in a Crimean Art Colony",
            "url": "https://www.nytimes.com/video/world/europe/100000003056344/rifts-in-a-crimean-art-colony.html",
            "published_date": "2014-08-21T00:22:41+0000",
            "category": "World",
            "abstract": "The Crimean town of Koktebel was a tolerant oasis for artists and writers in the midst of Soviet repression. Now, its residents are divided by the Russian annexation of Crimea.",
            "image_url": "https://www.nytimes.com/images/2014/08/21/world/CRIMEA-2/CRIMEA-2-articleLarge.jpg"
        },
        {
            "title": "Annexation of Crimea Divides an Artist Colony Founded on Tolerance",
            "url": "https://www.nytimes.com/2014/08/21/world/europe/annexation-of-crimea-divides-an-artist-colony-founded-on-tolerance.html",
            "published_date": "2014-08-21T00:28:49+0000",
            "category": "World",
            "abstract": "The light and landscape of coastal Koktebel has drawn artists for nearly a decade, but Russia\u2019s annexation of Crimea has split the normally peaceful oasis into feuding factions.",
            "image_url": null
        },
        {
            "title": "Ebola and the Problem of Panic",
            "url": "https://www.nytimes.com/video/world/100000003066732/ebola-and-the-problem-of-panic.html",
            "published_date": "2014-08-21T00:48:03+0000",
            "category": "World",
            "abstract": "Unrest in a slum in Monrovia, Liberia, is a case study for the panic and challenges doctors and patients face in poor, densely populated urban areas.",
            "image_url": "https://www.nytimes.com/images/2014/08/20/multimedia/ebola-slums/ebola-slums-articleLarge.jpg"
        },
        {
            "title": "A New Entry Is Shaking Up Brazil\u2019s Vote",
            "url": "https://www.nytimes.com/2014/08/21/world/americas/a-newcomer-is-shaking-up-brazils-vote.html",
            "published_date": "2014-08-21T00:51:44+0000",
            "category": "World",
            "abstract": "Marina Silva is emerging as one of the most disruptive figures in Brazilian politics in a generation, with a chance to be elected president.",
            "image_url": "https://www.nytimes.com/images/2014/08/21/world/21brazil/21brazil-articleLarge.jpg"
        },
        {
            "title": "From Missouri to Syria, Journalists Are Becoming Targets",
            "url": "https://www.nytimes.com/2014/08/21/world/middleeast/from-arrests-to-beheadings-conflict-reporting-takes-harsh-toll-on-journalists.html",
            "published_date": "2014-08-21T01:16:41+0000",
            "category": "World",
            "abstract": "Reporters, editors and those who monitor the freedom of the press describe a harsh environment for reporters, in the United States and abroad.",
            "image_url": null
        }
    ],
    "2014-08-22": [
        {
            "title": "German Broadcaster Fires Chinese Blogger",
            "url": "https://www.nytimes.com/2014/08/22/world/europe/german-broadcaster-fires-chinese-blogger.html",
            "published_date": "2014-08-22T00:50:24+0000",
            "category": "World",
            "abstract": "Many commentators on Chinese-language social media see hidden motives in the firing of Su Yutong, a prolific blogger on Deutsche Welle\u2019s Chinese-language website.",
            "image_url": "https://www.nytimes.com/images/2014/08/22/world/dissident/dissident-articleLarge.jpg"
        },
        {
            "title": "In Steps of Grandfather, a German Soldier in France",
            "url": "https://www.nytimes.com/2014/08/22/world/europe/exploring-a-world-war-i-battlefield-100-years-later.html",
            "published_date": "2014-08-22T01:04:45+0000",
            "category": "World",
            "abstract": "A reporter\u2019s grandfather was among the multitudes of German soldiers who stormed into France and Belgium and left some 27,000 French soldiers dead 100 years ago.",
            "image_url": "https://www.nytimes.com/images/2014/08/22/world/FAMILY-1/FAMILY-1-articleLarge.jpg"
        },
        {
            "title": "Foreign Minister Ahmet Davutoglu Nominated to Be Turkey\u2019s Next Premier",
            "url": "https://www.nytimes.com/2014/08/22/world/europe/foreign-minister-nominated-to-be-turkeys-next-premier.html",
            "published_date": "2014-08-22T01:17:51+0000",
            "category": "World",
            "abstract": "Turkey\u2019s governing party nominated Ahmet Davutoglu to succeed President-elect Recep Tayyip Erdogan as prime minister and party chairman.",
            "image_url": "https://www.nytimes.com/images/2014/08/22/world/TURKEY/TURKEY-articleLarge.jpg"
        },
        {
            "title": "Share Your Family\u2019s World War I History",
            "url": "https://www.nytimes.com/interactive/2014/08/22/world/europe/22family-callout.html",
            "published_date": "2014-08-22T01:20:28+0000",
            "category": "World",
            "abstract": "The New York Times invites you to share your family\u2019s story from World War I, and describe efforts you have made to learn about how that war affected your family.",
            "image_url": "https://www.nytimes.com/images/2014/08/22/world/22-family-social/22-family-social-articleLarge.jpg"
        },
        {
            "title": "Telling Blows Against Hamas",
            "url": "https://www.nytimes.com/slideshow/2014/08/22/world/middleeast/20140822-GAZA.html",
            "published_date": "2014-08-22T01:52:03+0000",
            "category": "World",
            "abstract": "Israel killed three top commanders of Hamas\u2019s armed wing in predawn airstrikes that also took other Palestinian lives.",
            "image_url": "https://www.nytimes.com/images/2014/08/22/world/20140822-GAZA-slide-SHKU/20140822-GAZA-slide-SHKU-articleLarge.jpg"
        }
    ],
    "2014-08-23": [
        {
            "title": "Two New Cases of Ebola Stem From Secondhand Contact",
            "url": "https://www.nytimes.com/2014/08/23/world/africa/two-new-cases-of-ebola-stem-from-indirect-contact.html",
            "published_date": "2014-08-23T01:12:23+0000",
            "category": "World",
            "abstract": "Although the cases in Nigeria involve the spouses of health workers who had cared for the Liberian-American who carried the virus, the country says its containment strategy is working.",
            "image_url": "https://www.nytimes.com/images/2014/08/23/world/EBOLA/EBOLA-articleLarge.jpg"
        },
        {
            "title": "U.S. Officials and Experts at Odds on Threat Posed by ISIS",
            "url": "https://www.nytimes.com/2014/08/23/us/politics/us-isnt-sure-just-how-much-to-fear-isis.html",
            "published_date": "2014-08-23T01:28:05+0000",
            "category": "U.S.",
            "abstract": "With the rapid advance of the Islamic State in Iraq and Syria, the rhetoric the Obama administration is using to describe the danger the group poses to the United States has escalated.",
            "image_url": "https://www.nytimes.com/images/2014/08/23/world/INTEL/INTEL-articleLarge.jpg"
        },
        {
            "title": "Gaza Talks Build at U.N.",
            "url": "https://www.nytimes.com/2014/08/23/world/middleeast/gaza-talks-build-at-un.html",
            "published_date": "2014-08-23T01:43:15+0000",
            "category": "World",
            "abstract": "Diplomats said Germany, France and Britain were involved in discussions about a possible Security Council resolution.",
            "image_url": null
        },
        {
            "title": "Blackouts in Egypt Prompt Accusations",
            "url": "https://www.nytimes.com/2014/08/23/world/middleeast/blackouts-in-egypt-prompt-accusations.html",
            "published_date": "2014-08-23T01:58:40+0000",
            "category": "World",
            "abstract": "Officials blamed supporters of a deposed leader, while others pointed fingers back at the government.",
            "image_url": null
        },
        {
            "title": "American\u2019s Star Power Unrivaled in Japan",
            "url": "https://www.nytimes.com/2014/08/23/world/asia/unknown-in-america-david-spector-carves-out-niche-in-japan.html",
            "published_date": "2014-08-23T02:07:53+0000",
            "category": "World",
            "abstract": "David Spector, with his bleach-blond hair and ability to deliver one-liners in flawless Japanese, has been a fixture in Japan\u2019s often raucous talk-show world for 30 years.",
            "image_url": "https://www.nytimes.com/images/2014/08/23/world/JAPAN/JAPAN-articleLarge.jpg"
        }
    ],
    "2014-08-24": [
        {
            "title": "China Says 8 Executed in Western Region; Charges Stem From Separatist Attacks ",
            "url": "https://www.nytimes.com/2014/08/25/world/asia/8-people-executed-in-xinjiang-on-terrorism-charges-china-says.html",
            "published_date": "2014-08-24T08:12:24+0000",
            "category": "World",
            "abstract": "The executions were the latest display of might by the Chinese government, which is trying to extinguish increasingly violent discontent among Uighurs.",
            "image_url": "https://www.nytimes.com/images/2014/08/24/world/asia/25XINJIANG/25XINJIANG-articleLarge.jpg"
        },
        {
            "title": "1889: Sarah Bernhardt\u2019s Courage in Real Death Scene",
            "url": "https://iht-retrospective.blogs.nytimes.com/2014/08/24/1889-sarah-bernhardts-courage-in-real-death-scene/",
            "published_date": "2014-08-24T09:46:36+0000",
            "category": "World",
            "abstract": "Highlights from the International Herald Tribune archives: The actress Sarah Bernhardt faces the funeral of her husband in 1889.",
            "image_url": "https://www.nytimes.com/images/2014/08/25/blogs/25iht-oldaug25-bernhardt/25iht-oldaug25-bernhardt-jumbo.jpg"
        },
        {
            "title": "In Eastern Ukraine, Rebel Mockery Amid Independence Celebration",
            "url": "https://www.nytimes.com/2014/08/25/world/europe/ukraine.html",
            "published_date": "2014-08-24T13:18:42+0000",
            "category": "World",
            "abstract": "As Ukrainians celebrated their country\u2019s independence, pro-Russian separatists in Donetsk staged a counter-parade to delight in the death and imprisonment of Ukrainian soldiers.",
            "image_url": "https://www.nytimes.com/images/2014/08/24/world/europe/25DONETSK/25DONETSK-articleLarge-v2.jpg"
        },
        {
            "title": "Strife in Libya Could Presage Long Civil War",
            "url": "https://www.nytimes.com/2014/08/25/world/africa/libyan-unrest.html",
            "published_date": "2014-08-24T14:22:22+0000",
            "category": "World",
            "abstract": "Libya is being torn apart by an escalating war among its patchwork of rival cities and tribes, and an assault that destroyed its main airport last month has exacerbated the nation\u2019s divisions.",
            "image_url": "https://www.nytimes.com/images/2014/08/24/world/middleeast/25LIBYA1/25LIBYA1-articleLarge.jpg"
        },
        {
            "title": "Ukraine Leader, Set to Meet Putin for Talks, Warns of Long Struggle",
            "url": "https://www.nytimes.com/2014/08/25/world/europe/ukraine-russia.html",
            "published_date": "2014-08-24T15:27:39+0000",
            "category": "World",
            "abstract": "As Ukraine celebrated its independence Sunday, President Petro O. Poroshenko, who is to meet with President Vladimir V. Putin of Russia in Belarus on Tuesday for peace talks, left little doubt that he saw Moscow as the source of the conflict.",
            "image_url": "https://www.nytimes.com/images/2014/08/24/world/europe/25UKRAINE-1/25UKRAINE-1-articleLarge.jpg"
        }
    ],
    "2014-08-25": [
        {
            "title": "Teenager Cites Ordeal as Captive of Israelis",
            "url": "https://www.nytimes.com/2014/08/25/world/middleeast/gaza-strip-palestinian-teenager-cites-ordeal-as-captive-of-israelis-soldiers.html",
            "published_date": "2014-08-25T00:28:43+0000",
            "category": "World",
            "abstract": "A 17-year-old Palestinian said Israeli soldiers detained him for five days, forcing him to search and dig for Hamas tunnels.",
            "image_url": "https://www.nytimes.com/images/2014/08/25/world/JP-TEEN/JP-TEEN-articleLarge-v2.jpg"
        },
        {
            "title": "Fishermen Cross an Imperceptible Line Into Enemy Waters",
            "url": "https://www.nytimes.com/2014/08/25/world/asia/fishermen-cross-an-imperceptible-line-into-enemy-waters.html",
            "published_date": "2014-08-25T00:39:26+0000",
            "category": "World",
            "abstract": "Several thousand fishermen, both Pakistani and Indian, have been arrested at sea in recent years, accused of crossing a border they cannot see and whose exact location is in dispute.",
            "image_url": "https://www.nytimes.com/images/2014/08/25/world/FISHERMEN/FISHERMEN-articleLarge.jpg"
        },
        {
            "title": "Israel Says Missile Strike Killed Hamas Official Handling \u2018Terror Funds\u2019",
            "url": "https://www.nytimes.com/2014/08/25/world/middleeast/israel-says-missile-strike-killed-hamas-official-handling-terror-funds.html",
            "published_date": "2014-08-25T01:04:44+0000",
            "category": "World",
            "abstract": "The Israeli military said the Hamas official had been responsible for the militant group\u2019s financial transactions.",
            "image_url": null
        },
        {
            "title": "Britain Appeals to Anti-Extremist Imams in Effort to Uproot Seeds of Radicalization",
            "url": "https://www.nytimes.com/2014/08/25/world/europe/nation-appeals-to-anti-extremist-imams-in-effort-to-uproot-seeds-of-radicalization.html",
            "published_date": "2014-08-25T01:21:27+0000",
            "category": "World",
            "abstract": "Britain has turned to the imams for help preventing British Muslims from adopting radical views, and for persuading militants to moderate their beliefs.",
            "image_url": "https://www.nytimes.com/images/2014/08/25/world/europe/25IMAM/25IMAM-articleLarge.jpg"
        },
        {
            "title": "ISIS Tightens Its Grip With Seizure of Air Base in Syria",
            "url": "https://www.nytimes.com/2014/08/25/world/middleeast/isis-militants-capture-air-base-from-syrian-government-forces.html",
            "published_date": "2014-08-25T01:24:05+0000",
            "category": "World",
            "abstract": "The fall of the Tabqa air base gave the militants effective control of Raqqa Province and highlighted the lack of local military forces that can effectively battle the group.",
            "image_url": "https://www.nytimes.com/images/2014/08/25/world/SYRIA/SYRIA-articleLarge.jpg"
        }
    ],
    "2014-08-26": [
        {
            "title": "Liberian Doctor Treated With an Experimental Drug Dies From Ebola",
            "url": "https://www.nytimes.com/2014/08/26/world/africa/liberian-doctor-treated-with-an-experimental-drug-dies-from-ebola.html",
            "published_date": "2014-08-26T00:28:17+0000",
            "category": "World",
            "abstract": "Dr. Abraham Borbor, deputy chief medical doctor at Liberia\u2019s largest hospital, received ZMapp \u2014 the same drug given to two infected Americans who survived.",
            "image_url": null
        },
        {
            "title": "U.S. Says It Told Qatar Not to Pay a Ransom",
            "url": "https://www.nytimes.com/2014/08/26/world/middleeast/us-says-it-told-qatar-not-to-pay-a-ransom.html",
            "published_date": "2014-08-26T00:44:54+0000",
            "category": "World",
            "abstract": "The Obama administration has insisted that it told the government of Qatar not to pay a ransom for the release of the captured journalist Peter Theo Curtis.",
            "image_url": null
        },
        {
            "title": "Ex-Diplomat for the Vatican Could Be Tried",
            "url": "https://www.nytimes.com/2014/08/26/world/americas/ex-diplomat-for-the-vatican-could-be-tried.html",
            "published_date": "2014-08-26T00:53:27+0000",
            "category": "World",
            "abstract": "The former ambassador to the Dominican Republic is accused of paying boys there to engage in sexual acts, and his diplomatic immunity has been revoked.",
            "image_url": "https://www.nytimes.com/images/2014/08/26/world/DOMINICAN/DOMINICAN-articleLarge.jpg"
        },
        {
            "title": "Poland Embraces Football That Has a Rougher Side",
            "url": "https://www.nytimes.com/2014/08/26/world/europe/poland-embraces-football-that-has-a-rougher-side.html",
            "published_date": "2014-08-26T01:03:24+0000",
            "category": "World",
            "abstract": "The most popular Polish sports \u2014 like volleyball \u2014 tend to avoid physical contact, but the Warsaw Eagles are cultivating a crowd that enjoys the rougher stuff.",
            "image_url": "https://www.nytimes.com/images/2014/08/26/world/FOOTBALL-1/FOOTBALL-1-articleLarge.jpg"
        },
        {
            "title": "In India, an App for Chats and for Keeping Secrets",
            "url": "https://www.nytimes.com/2014/08/26/world/asia/in-india-an-app-for-chats-and-for-keeping-secrets.html",
            "published_date": "2014-08-26T01:21:42+0000",
            "category": "World",
            "abstract": "The Hike instant messaging system lets users filter information to cloak aspects of their social lives from their parents.",
            "image_url": null
        }
    ],
    "2014-08-27": [
        {
            "title": "A Banker\u2019s Bold Vision Inspires an Arts Center, and Neighbors\u2019 Doubts",
            "url": "https://www.nytimes.com/2014/08/27/world/europe/a-bankers-bold-vision-inspires-an-arts-center-and-neighbors-doubts.html",
            "published_date": "2014-08-27T00:19:17+0000",
            "category": "World",
            "abstract": "The Centro Bot\u00edn, designed by Renzo Piano, is rising in the northern city of Santander, along with complaints that public space is being exploited.",
            "image_url": "https://www.nytimes.com/images/2014/08/27/world/SUB-SANTANDER-2/SUB-SANTANDER-2-articleLarge.jpg"
        },
        {
            "title": "Hard-Line Splinter Group, Galvanized by ISIS, Emerges From Pakistani Taliban",
            "url": "https://www.nytimes.com/2014/08/27/world/asia/hard-line-splinter-group-galvanized-by-isis-emerges-from-pakistani-taliban.html",
            "published_date": "2014-08-27T00:59:55+0000",
            "category": "World",
            "abstract": "The new group, known as Jamaat-e-Ahrar, is composed of disaffected Taliban factions from four of the seven tribal districts along the Pakistan border with Afghanistan.",
            "image_url": null
        },
        {
            "title": "U.S. Fires on an Iranian Boat",
            "url": "https://www.nytimes.com/2014/08/27/world/middleeast/us-fires-on-an-iranian-boat.html",
            "published_date": "2014-08-27T01:07:20+0000",
            "category": "World",
            "abstract": "A United States Coast Guard vessel fired Tuesday on an Iranian boat in the Persian Gulf in what the Defense Department said was a defensive maneuver.",
            "image_url": null
        },
        {
            "title": "Turkey: Chinese Workers Abducted",
            "url": "https://www.nytimes.com/2014/08/27/world/europe/turkey-chinese-workers-abducted.html",
            "published_date": "2014-08-27T01:11:50+0000",
            "category": "World",
            "abstract": "Kurdish separatists kidnapped three Chinese engineers in an area near a power plant in Turkey\u2019s southeast, a regional government official said Tuesday.",
            "image_url": null
        },
        {
            "title": "U.S. Mobilizes Allies to Widen Assault on ISIS",
            "url": "https://www.nytimes.com/2014/08/27/world/middleeast/us-mobilizes-allies-to-widen-assault-on-isis.html",
            "published_date": "2014-08-27T01:28:35+0000",
            "category": "World",
            "abstract": "President Obama is nearing a decision to authorize airstrikes and airdrops around Amerli, an Iraqi town that has been under siege by militants for more than two months.",
            "image_url": "https://www.nytimes.com/images/2014/08/27/world/STRIKE/STRIKE-articleLarge.jpg"
        }
    ],
    "2014-08-28": [
        {
            "title": "Proposing New Capital Is Old Idea in Argentina",
            "url": "https://www.nytimes.com/2014/08/28/world/americas/proposing-new-capital-is-old-idea-in-argentina.html",
            "published_date": "2014-08-28T00:23:26+0000",
            "category": "World",
            "abstract": "President Cristina Fern\u00e1ndez de Kirchner\u2019s suggestion to consider making Santiago del Estero the nation\u2019s capital reflects longstanding tension between Buenos Aires and Argentina\u2019s provinces.",
            "image_url": null
        },
        {
            "title": "From a Compound in the Brazilian Hills, Excellence in Math Emerges",
            "url": "https://www.nytimes.com/2014/08/28/world/americas/from-a-compound-in-the-brazilian-hills-excellence-in-math-emerges.html",
            "published_date": "2014-08-28T00:47:04+0000",
            "category": "World",
            "abstract": "The National Institute for Pure and Applied Mathematics in Rio is gaining attention as a hidden gem in a country with few world-renowned educational institutions.",
            "image_url": "https://www.nytimes.com/images/2014/08/28/world/BRAZILMATH2/BRAZILMATH2-articleLarge.jpg"
        },
        {
            "title": "Military Skill and Terrorist Technique Fuel Success of ISIS",
            "url": "https://www.nytimes.com/2014/08/28/world/middleeast/army-know-how-seen-as-factor-in-isis-successes.html",
            "published_date": "2014-08-28T01:05:13+0000",
            "category": "World",
            "abstract": "As fighters continue to seize territory, the Islamic State in Iraq and Syria has built an effective management structure of mostly middle-aged Iraqis, including many military officers under Saddam Hussein.",
            "image_url": "https://www.nytimes.com/images/2014/08/28/world/ISIS/ISIS-articleLarge.jpg"
        },
        {
            "title": "Skirmishes Put Feeling of Wartime on India-Pakistan Border",
            "url": "https://www.nytimes.com/2014/08/28/world/asia/skirmishes-put-feeling-of-wartime-on-india-pakistan-border.html",
            "published_date": "2014-08-28T01:12:37+0000",
            "category": "World",
            "abstract": "Nightly artillery firing across the border intensified in mid-August and reportedly has killed two Indian civilians and four Pakistani civilians.",
            "image_url": "https://www.nytimes.com/images/2014/08/28/world/INDIA/INDIA-articleLarge.jpg"
        },
        {
            "title": "Iran Altering Reactor in Bid for Nuclear Deal",
            "url": "https://www.nytimes.com/2014/08/28/world/middleeast/iran-altering-reactor-in-bid-for-nuclear-deal.html",
            "published_date": "2014-08-28T01:23:59+0000",
            "category": "World",
            "abstract": "The nation\u2019s top nuclear official said the reactor would be redesigned to limit the amount of plutonium it could produce.",
            "image_url": "https://www.nytimes.com/images/2014/08/28/world/NUCLEAR/NUCLEAR-articleLarge.jpg"
        }
    ],
    "2014-08-29": [
        {
            "title": "Theme Park Offers Respite for War-Weary Iraqis",
            "url": "https://www.nytimes.com/2014/08/29/world/middleeast/theme-park-offers-respite-for-war-weary-iraqis.html",
            "published_date": "2014-08-29T00:06:41+0000",
            "category": "World",
            "abstract": "Most people at Happy Park in Iraqi Kurdistan \u2014 many from wealthy families, or longtime residents seeking a break \u2014 were glad to have any kind of escape from ISIS militants.",
            "image_url": "https://www.nytimes.com/images/2014/08/29/world/ZAKHO-3/ZAKHO-3-articleLarge.jpg"
        },
        {
            "title": "With Gaza War, Movement to Boycott Israel Gains Momentum in Europe",
            "url": "https://www.nytimes.com/2014/08/29/world/europe/with-gaza-war-movement-to-boycott-israel-gains-momentum-in-europe.html",
            "published_date": "2014-08-29T00:10:52+0000",
            "category": "World",
            "abstract": "The war in Gaza and its aftermath have inflamed opinion in Europe, analysts say, and are likely to increase support for campaigns to divest from and penalize Israel.",
            "image_url": "https://www.nytimes.com/images/2014/08/29/world/JP-EUROPEISRAEL/JP-EUROPEISRAEL-articleLarge.jpg"
        },
        {
            "title": "An Israeli App Tracking the Gaza Conflict Has Followers Near and Far",
            "url": "https://www.nytimes.com/2014/08/29/world/middleeast/an-israeli-app-tracking-the-gaza-conflict-has-followers-near-and-far.html",
            "published_date": "2014-08-29T00:34:17+0000",
            "category": "World",
            "abstract": "More than one million people have downloaded Red Alert, an app tracking rocket fire from Gaza that alerts users with a siren similar to those heard in the south of Israel.",
            "image_url": "https://www.nytimes.com/images/2014/08/29/world/ISRAEL/ISRAEL-articleLarge.jpg"
        },
        {
            "title": "U.S. Identifies Citizens Joining Rebels in Syria, Including ISIS",
            "url": "https://www.nytimes.com/2014/08/29/world/middleeast/us-identifies-citizens-joining-rebels-in-syria.html",
            "published_date": "2014-08-29T01:32:10+0000",
            "category": "World",
            "abstract": "Nearly a dozen Americans are known to have traveled to Syria to fight for the Islamic State in Iraq and Syria, the militant group that the Obama administration says poses the greatest threat to the United States since Al Qaeda before the Sept. 11, 2001, attacks.",
            "image_url": null
        },
        {
            "title": "Air Encounter More Likely to Cause Alarm Than Change",
            "url": "https://www.nytimes.com/2014/08/29/world/asia/air-encounter-more-likely-to-cause-alarm-than-change.html",
            "published_date": "2014-08-29T02:10:37+0000",
            "category": "World",
            "abstract": "The Pentagon called a Chinese fighter pilot\u2019s approaching an American spy plane \u201cvery dangerous,\u201d but the Beijing-Washington division on surveillance flights will probably remain.",
            "image_url": null
        }
    ],
    "2014-08-30": [
        {
            "title": "Quarantine for Ebola Lifted in Liberia Slum",
            "url": "https://www.nytimes.com/2014/08/30/world/africa/quarantine-for-ebola-lifted-in-liberia-slum.html",
            "published_date": "2014-08-30T00:06:52+0000",
            "category": "World",
            "abstract": "The president of Liberia had rejected the advice of Ebola experts in quarantining the West Point neighborhood, a move that resulted in deadly clashes.",
            "image_url": null
        },
        {
            "title": "Iraqi Kurds Expand Autonomy as ISIS Reorders the Landscape",
            "url": "https://www.nytimes.com/2014/08/30/world/middleeast/iraqi-kurds-expand-autonomy-as-isis-reorders-the-landscape.html",
            "published_date": "2014-08-30T00:45:22+0000",
            "category": "World",
            "abstract": "The ISIS invasion has physically cut off most of Kurdistan from the rest of Shiite-dominated Iraq and encouraged the Iraqi Kurds in their drive for expanded autonomy.",
            "image_url": "https://www.nytimes.com/images/2014/08/30/world/JP-KURDS-1/JP-KURDS-1-articleLarge.jpg"
        },
        {
            "title": "Leadership and Calm Are Urged in Ebola Outbreak",
            "url": "https://www.nytimes.com/2014/08/30/science/leadership-and-calm-are-urged-in-outbreak.html",
            "published_date": "2014-08-30T00:59:01+0000",
            "category": "Science",
            "abstract": "Leadership and help from Western nations are needed to eradicate the virus in West Africa, according to some of the top experts in disease eradication.",
            "image_url": "https://www.nytimes.com/images/2014/08/30/world/EBOLA/EBOLA-articleLarge.jpg"
        },
        {
            "title": "U.S. Colleges See Little Risk From Ebola, but Depend on Students to Speak Up",
            "url": "https://www.nytimes.com/2014/08/30/us/us-colleges-see-little-risk-from-ebola-but-depend-on-students-to-speak-up.html",
            "published_date": "2014-08-30T01:06:14+0000",
            "category": "U.S.",
            "abstract": "Universities and colleges in the United States also admit that they have limited ability to track students\u2019 travels or their health.",
            "image_url": null
        },
        {
            "title": "50 Days of War Leave Israelis and Palestinians Only More Entrenched",
            "url": "https://www.nytimes.com/2014/08/30/world/middleeast/50-days-of-war-leave-israelis-and-palestinians-only-more-entrenched.html",
            "published_date": "2014-08-30T01:16:48+0000",
            "category": "World",
            "abstract": "Both sides claimed victory, but the cease-fire is uneasy. Israeli citizens feel more insecure than before, and Hamas failed to win the concessions it demanded.",
            "image_url": "https://www.nytimes.com/images/2014/08/30/world/JERUSALEM/JERUSALEM-articleLarge.jpg"
        }
    ],
    "2014-08-31": [
        {
            "title": "U.S. Strikes Militants Besieging Turkmen in Iraq",
            "url": "https://www.nytimes.com/2014/08/31/world/middleeast/us-strikes-militants-besieging-turkmen-in-iraq.html",
            "published_date": "2014-08-31T02:34:43+0000",
            "category": "World",
            "abstract": "American planes struck the Islamic State in Iraq and Syria, and dropped food, water and aid near the northern town of Amerli.",
            "image_url": null
        },
        {
            "title": "China Restricts Voting Reforms for Hong Kong",
            "url": "https://www.nytimes.com/2014/09/01/world/asia/hong-kong-elections.html",
            "published_date": "2014-08-31T09:08:10+0000",
            "category": "World",
            "abstract": "China\u2019s legislature laid down strict limits to proposed voting reforms in Hong Kong, drawing battle lines in what could be a deepening confrontation over the future of the city and of China.",
            "image_url": "https://www.nytimes.com/images/2014/09/01/world/JP-HONG-KONG-1/JP-HONG-KONG-1-articleLarge.jpg"
        },
        {
            "title": "1939: Britain on War Basis With Reservists Called, Navy Fully Mobilized, Telephone Connection Cut",
            "url": "https://iht-retrospective.blogs.nytimes.com/2014/08/31/1939-britain-on-war-basis-with-reservists-called-navy-fully-mobilized-telephone-connection-cut/",
            "published_date": "2014-08-31T10:08:51+0000",
            "category": "World",
            "abstract": "From the International Herald Tribune archives: Britain starts preparing for war in 1939.",
            "image_url": null
        },
        {
            "title": "Pakistani Army Calls for Calm After Protest Turns Deadly",
            "url": "https://www.nytimes.com/2014/09/01/world/asia/pakistani-unrest.html",
            "published_date": "2014-08-31T11:09:43+0000",
            "category": "World",
            "abstract": "At least three people died in clashes with the police when demonstrators, calling for Prime Minister Nawaz Sharif\u2019s resignation, marched toward his official residence.",
            "image_url": "https://www.nytimes.com/images/2014/08/31/world/asia/01PAKISTAN1/01PAKISTAN1-articleLarge.jpg"
        },
        {
            "title": "Affiliate of Al Qaeda Confirms Capture of U.N. Peacekeepers in Syria",
            "url": "https://www.nytimes.com/2014/09/01/world/middleeast/un-peacekeepers-captured-in-syria.html",
            "published_date": "2014-08-31T11:45:57+0000",
            "category": "World",
            "abstract": "The Nusra Front, the Syrian branch of Al Qaeda, said it had seized more than 40 peacekeepers because the United Nations failed to help the people of Syria during the country\u2019s civil war.",
            "image_url": "https://www.nytimes.com/images/2014/08/31/world/middleeast/01GOLAN/01GOLAN-articleLarge.jpg"
        }
    ]
}