{
    "2014-07-01": [
        {
            "title": "Ukrainian President Ends Cease-Fire With Rebels",
            "url": "https://www.nytimes.com/2014/07/01/world/europe/ukrainian-president-ends-cease-fire-with-rebels.html",
            "published_date": "2014-07-01T01:01:59+0000",
            "category": "World",
            "abstract": "President Petro O. Poroshenko ended a 10-day cease-fire, saying that rebels had not put down their weapons and had persisted in attacking government troops.",
            "image_url": "https://www.nytimes.com/images/2014/07/01/world/UKRAINE/UKRAINE-articleLarge.jpg"
        },
        {
            "title": "For Iraq, Potential Leader With a Tarnished Past",
            "url": "https://www.nytimes.com/2014/07/01/world/middleeast/for-iraq-potential-leader-with-a-tarnished-past.html",
            "published_date": "2014-07-01T01:17:40+0000",
            "category": "World",
            "abstract": "Ahmad Chalabi, once championed by the Bush administration as a possible leader for Iraq and then pushed aside for faulty depictions of weapons of mass destruction, has re-emerged in talks among the country\u2019s political parties as a contender for prime minister.",
            "image_url": "https://www.nytimes.com/images/2014/07/01/world/middleeast/IRAQ/IRAQ-articleLarge.jpg"
        },
        {
            "title": "ISIS\u2019 Goals for Iraq and Syria",
            "url": "https://www.nytimes.com/video/world/middleeast/100000002974316/isis-goals-for-iraq-and-syria.html",
            "published_date": "2014-07-01T01:18:14+0000",
            "category": "World",
            "abstract": "Background on ISIS, the Islamic State in Iraq and Syria.",
            "image_url": "https://www.nytimes.com/images/2014/07/23/world/23RAQQA/23RAQQA-articleLarge-v3.jpg"
        },
        {
            "title": "A Long History of Rebellion in the Mountains of Pakistan",
            "url": "https://www.nytimes.com/2014/07/01/world/asia/Waziristan-Region-of-Pakistan-Has-Long-History-of-Rebellion.html",
            "published_date": "2014-07-01T01:33:44+0000",
            "category": "World",
            "abstract": "The Waziristan region of Pakistan\u2019s northwest is known as a haven for militants, with a 150-year history of insurgent campaigns.",
            "image_url": null
        },
        {
            "title": "ISIS Threatens Al Qaeda as Flagship Movement of Extremists",
            "url": "https://www.nytimes.com/2014/07/01/world/middleeast/isis-threatens-al-qaeda-as-flagship-movement-of-extremists.html",
            "published_date": "2014-07-01T01:34:54+0000",
            "category": "World",
            "abstract": "The question is whether the new group, which now calls itself simply the Islamic State, will endure.",
            "image_url": null
        }
    ],
    "2014-07-02": [
        {
            "title": "Tourists on Trial in a North Korea Angry at the U.S.",
            "url": "https://www.nytimes.com/2014/07/02/world/asia/korean-anger-may-be-behind-trials-of-tourists.html",
            "published_date": "2014-07-02T01:03:38+0000",
            "category": "World",
            "abstract": "North Korea\u2019s decision to try two Americans could reflect the isolated nation\u2019s frustration that the United States is ignoring it, experts said.",
            "image_url": null
        },
        {
            "title": "Limits to Books in Prison Draw Creative Foes",
            "url": "https://www.nytimes.com/2014/07/02/world/europe/limits-to-books-in-prison-draw-creative-foes.html",
            "published_date": "2014-07-02T01:03:47+0000",
            "category": "World",
            "abstract": "Restrictions on the flow of books into British prisons create a firestorm among authors and reform activists, who say that reading is a human right.",
            "image_url": "https://www.nytimes.com/images/2014/07/02/world/BOOKS/BOOKS-articleLarge-v3.jpg"
        },
        {
            "title": "Anatoly Kornukov, Who Led Russian Air Force, Dies at 72",
            "url": "https://www.nytimes.com/2014/07/02/world/europe/anatoly-kornukov-who-led-russian-air-force-dies-at-72.html",
            "published_date": "2014-07-02T01:36:18+0000",
            "category": "World",
            "abstract": "Gen. Anatoly Kornukov ordered Korean Air Lines Flight 007, a commercial jet with 269 people aboard, shot down in 1983 after it strayed into Soviet airspace.",
            "image_url": "https://www.nytimes.com/images/2014/07/02/world/KORNUKOV-obit/KORNUKOV-obit-articleLarge.jpg"
        },
        {
            "title": "Deeply Divided Israel Unites in Grief and Sees a Larger Purpose",
            "url": "https://www.nytimes.com/2014/07/02/world/middleeast/deeply-divided-israel-unites-in-grief-and-sees-a-larger-purpose.html",
            "published_date": "2014-07-02T01:52:25+0000",
            "category": "World",
            "abstract": "A day after the bodies of three kidnapped Israeli teenagers were found in the West Bank, thousands gathered to bury them side by side, wrapped in Israeli flags.",
            "image_url": "https://www.nytimes.com/images/2014/07/02/world/ISRAEL-2/ISRAEL-1-1404255615337-articleLarge.jpg"
        },
        {
            "title": "Benghazi Suspect Said to Corroborate Important Details of Attacks",
            "url": "https://www.nytimes.com/2014/07/02/world/middleeast/benghazi-suspect-said-to-corroborate-details-of-attacks.html",
            "published_date": "2014-07-02T03:15:54+0000",
            "category": "World",
            "abstract": "American officials said Ahmed Abu Khattala has not incriminated himself in the killing of Ambassador J. Christopher Stevens and three others, but he has provided interrogators with \u201ckey facts\u201d about what occurred on the day of the attacks.",
            "image_url": "https://www.nytimes.com/images/2014/07/02/world/middleeast/02KHATTALA/02KHATTALA-articleLarge.jpg"
        }
    ],
    "2014-07-03": [
        {
            "title": "Pakistan Approves Sweeping Antiterror Bill, Prompting Warnings From Rights Groups",
            "url": "https://www.nytimes.com/2014/07/03/world/asia/pakistan-approves-sweeping-antiterror-bill-prompting-warnings-from-rights-groups.html",
            "published_date": "2014-07-03T00:07:33+0000",
            "category": "World",
            "abstract": "The act allows security forces to shoot suspects on sight, arrest suspects without warrant and withhold information about where detainees are being held or what they are being charged with.",
            "image_url": null
        },
        {
            "title": "Government of Ecuador Can Sue Fugitive Bankers in U.S.",
            "url": "https://www.nytimes.com/2014/07/03/world/americas/ecuador-government-can-sue-fugitive-bankers-in-us.html",
            "published_date": "2014-07-03T00:26:09+0000",
            "category": "World",
            "abstract": "Ecuador has the right to sue a pair of fugitive bankers in courts in the United States to recover millions of dollars that the men are accused of embezzling, a Florida appellate court has ruled.",
            "image_url": null
        },
        {
            "title": "Nicolas Sarkozy\u2019s Many Legal Hurdles",
            "url": "https://www.nytimes.com/video/world/europe/100000002978871/nicolas-sarkozys-many-legal-hurdles.html",
            "published_date": "2014-07-03T00:39:39+0000",
            "category": "World",
            "abstract": "The former president of France is facing numerous legal challenges as he considers running for the top office again in 2017.",
            "image_url": "https://www.nytimes.com/images/2014/07/02/world/europe/03SARKOZY/03SARKOZY-articleLarge-v2.jpg"
        },
        {
            "title": "As Deadline Nears for an Iran Nuclear Pact, the Fingers Are Pointing",
            "url": "https://www.nytimes.com/2014/07/03/world/middleeast/as-deadline-nears-for-an-iran-nuclear-pact-the-fingers-are-pointing.html",
            "published_date": "2014-07-03T01:07:25+0000",
            "category": "World",
            "abstract": "With less than three weeks until a deadline for an agreement on Iran\u2019s nuclear future, public sparring rests on the larger narrative of whether Iran should settle its estrangement from the West.",
            "image_url": null
        },
        {
            "title": "Scorn for \u2018Tiger Xu,\u2019 From Official and Unofficial Sources",
            "url": "https://sinosphere.blogs.nytimes.com/2014/07/02/scorn-for-tiger-xu-from-official-and-unofficial-sources/",
            "published_date": "2014-07-03T03:33:20+0000",
            "category": "World",
            "abstract": "Chinese state-run newspapers and social media users alike are expressing contempt for Xu Caihou, a retired senior general expelled from the Communist Party over corruption allegations.",
            "image_url": "https://www.nytimes.com/images/2014/07/02/world/02sino-xu/02sino-xu-articleLarge.jpg"
        }
    ],
    "2014-07-04": [
        {
            "title": "Video Shows Abduction of Slain Palestinian Teenager, Family Says",
            "url": "https://www.nytimes.com/2014/07/04/world/middleeast/video-shows-abduction-of-slain-palestinian-teenager-family-says.html",
            "published_date": "2014-07-04T00:35:10+0000",
            "category": "World",
            "abstract": "Video released by the family of Muhammad Abu Khdeir, a 16-year-old Palestinian killed Wednesday, appears to show his abduction from a street in East Jerusalem.",
            "image_url": null
        },
        {
            "title": "Brazil Comes Around as the World Cup Plays On",
            "url": "https://www.nytimes.com/2014/07/04/world/americas/brazil-comes-around-as-the-world-cup-plays-on.html",
            "published_date": "2014-07-04T01:02:36+0000",
            "category": "World",
            "abstract": "The tournament has not produced the disasters some feared, and many Brazilians who were angry about lavish spending on the event cannot help getting caught up in its spirit.",
            "image_url": "https://www.nytimes.com/images/2014/07/04/world/BRAZIL-1/BRAZIL-1-articleLarge.jpg"
        },
        {
            "title": "Kurdish Officials Seek More Autonomy in Any Deal With a New Government",
            "url": "https://www.nytimes.com/2014/07/04/world/middleeast/kurdish-officials-doubtful-of-a-new-iraqi-government-still-seek-autonomy.html",
            "published_date": "2014-07-04T01:13:36+0000",
            "category": "World",
            "abstract": "Leaders in Kurdistan have said they will not participate in a unified government unless Baghdad grants the region expanded self-rule and accepts the occupation of Kirkuk.",
            "image_url": "https://www.nytimes.com/images/2014/07/04/world/KURDS1/KURDS1-articleLarge.jpg"
        },
        {
            "title": "Mood in Israel After Kidnappings",
            "url": "https://www.nytimes.com/video/world/middleeast/100000002981575/mood-in-israel-after-kidnappings.html",
            "published_date": "2014-07-04T01:25:29+0000",
            "category": "World",
            "abstract": "Israelis and Palestinians are caught in another cycle of violence with little hope for a political solution.",
            "image_url": "https://www.nytimes.com/images/2014/07/07/world/middleeast/israel-video/israel-video-articleLarge.jpg"
        },
        {
            "title": "Obama\u2019s Blueprint for Fighting Terrorism Collides With Reality in Iraq",
            "url": "https://www.nytimes.com/2014/07/04/world/obamas-no-war-plan-for-fighting-terrorism-meets-reality-in-iraq.html",
            "published_date": "2014-07-04T01:51:14+0000",
            "category": "World",
            "abstract": "The seizing of large parts of Iraq by Sunni militants has laid bare the limitations of a terrorism policy that relies on the cooperation of often balky and overmatched partners.",
            "image_url": null
        }
    ],
    "2014-07-05": [
        {
            "title": "Poised to Gain in Iraq Crisis, Kurds Face New Barriers to Autonomy",
            "url": "https://www.nytimes.com/2014/07/05/world/middleeast/poised-to-gain-in-iraq-crisis-kurds-face-new-barriers-to-autonomy.html",
            "published_date": "2014-07-05T00:59:54+0000",
            "category": "World",
            "abstract": "Although exporting its vast oil supply would give the Kurdish government leverage in its push for sovereignty, opposition from other nations has left the region\u2019s future uncertain.",
            "image_url": null
        },
        {
            "title": "Refugee Camp for Syrians in Jordan Evolves as a Do-It-Yourself City",
            "url": "https://www.nytimes.com/2014/07/05/world/middleeast/zaatari-refugee-camp-in-jordan-evolves-as-a-do-it-yourself-city.html",
            "published_date": "2014-07-05T01:12:14+0000",
            "category": "World",
            "abstract": "As the sprawling Zaatari camp evolves into an informal city \u2014 with an economy and even gentrification \u2014 aid workers say camps can be potential urban incubators that benefit host countries like Jordan.",
            "image_url": null
        },
        {
            "title": "Emilio \u00c1lvarez Montalv\u00e1n, Nicaragua\u2019s Pro-Democracy Sage, Dies at 94",
            "url": "https://www.nytimes.com/2014/07/05/world/americas/emilio-alvarez-montalvan-nicaraguas-pro-democracy-sage-dies-at-94.html",
            "published_date": "2014-07-05T02:22:39+0000",
            "category": "World",
            "abstract": "Dr. \u00c1lvarez was an ophthalmologist, former guerrilla, political prisoner, diplomat and trenchant critic of dictatorship, and he was often called the wisest man in Nicaragua.",
            "image_url": "https://www.nytimes.com/images/2014/07/06/world/dog-alvarez-obit/dog-alvarez-obit-articleLarge-v2.jpg"
        },
        {
            "title": "Autopsy Suggests Palestinian Teenager Was Burned to Death After Abduction",
            "url": "https://www.nytimes.com/2014/07/06/world/middleeast/autopsy-suggests-palestinian-boy-was-burned-alive-reports-say.html",
            "published_date": "2014-07-05T10:50:51+0000",
            "category": "World",
            "abstract": "An examination of the teenager who was snatched from an East Jerusalem street and slain this week found soot in his lungs, according to a senior Palestinian official briefed on the early results.",
            "image_url": "https://www.nytimes.com/images/2014/07/06/world/06ISRAEL/06ISRAEL-articleLarge.jpg"
        },
        {
            "title": "Pro-Russian Fighters Routed From Stronghold, Ukraine Says",
            "url": "https://www.nytimes.com/2014/07/06/world/europe/ukraine-and-rebels-clash-in-slovyansk.html",
            "published_date": "2014-07-05T13:40:50+0000",
            "category": "World",
            "abstract": "The Ukrainian government said Saturday that it had pushed pro-Russian fighters out of Slovyansk, a long-blockaded rebel stronghold where some of the fiercest fighting has occurred during the more than three-month separatist insurrection.",
            "image_url": "https://www.nytimes.com/images/2014/07/06/world/UKRAINE-2/UKRAINE-2-articleLarge.jpg"
        }
    ],
    "2014-07-06": [
        {
            "title": "1914: America Sends a Million Dollars of Gold to Mexico",
            "url": "https://iht-retrospective.blogs.nytimes.com/2014/07/06/1914-america-sends-a-million-dollars-of-gold-to-mexico/",
            "published_date": "2014-07-06T10:44:19+0000",
            "category": "World",
            "abstract": "Highlights from the International Herald Tribune archives: Mexican rebels sponsored by money from the United States in 1914.",
            "image_url": null
        },
        {
            "title": "6 Israelis Held Over the Killing of Palestinian",
            "url": "https://www.nytimes.com/2014/07/07/world/middleeast/israel-palestinians-muhammad-abu-khdeir.html",
            "published_date": "2014-07-06T12:12:42+0000",
            "category": "World",
            "abstract": "A group of Israelis was arrested in what one official described as a revenge killing. Prime Minister Benjamin Netanyahu pledged to pursue the case and said, \u201cWe do not differentiate between terrorists.\u201d",
            "image_url": "https://www.nytimes.com/images/2014/07/07/world/sub-ISRAEL-1/sub-ISRAEL-1-articleLarge.jpg"
        },
        {
            "title": "Malaysia Is Sending More Ships to Search for Jetliner",
            "url": "https://www.nytimes.com/2014/07/07/world/asia/malaysia-sending-more-ships-to-search-for-plane.html",
            "published_date": "2014-07-06T13:10:28+0000",
            "category": "World",
            "abstract": "The Malaysian government said Sunday that it would step up efforts to search the southern Indian Ocean for Malaysia Airlines\u2019 missing Flight 370.",
            "image_url": "https://www.nytimes.com/images/2014/07/06/world/asia/07MALAYSIA/07MALAYSIA-articleLarge.jpg"
        },
        {
            "title": "Gruesome Attacks in Kenyan Villages Heighten Fears of a Nation on Edge ",
            "url": "https://www.nytimes.com/2014/07/07/world/africa/deadly-attacks-in-kenya.html",
            "published_date": "2014-07-06T18:08:30+0000",
            "category": "World",
            "abstract": "The violence, in which the victims had their hands bound and their throats slit, was the latest of a string of attacks with ethnic undercurrents that comes at a time of rising political tensions.",
            "image_url": "https://www.nytimes.com/images/2014/07/07/world/KENYA-promo/KENYA-articleLarge.jpg"
        },
        {
            "title": "1964: Fans Scream for Beatles at Movie Premiere",
            "url": "https://iht-retrospective.blogs.nytimes.com/2014/07/06/1964-fans-scream-for-beatles-at-movie-premiere/",
            "published_date": "2014-07-06T18:26:54+0000",
            "category": "World",
            "abstract": "Highlights from the International Herald Tribune archives: A crowd of fans greeted the Beatles at the premiere of their first film, in 1964.",
            "image_url": null
        }
    ],
    "2014-07-07": [
        {
            "title": "Ukraine Military Finds Its Footing Against Pro-Russian Rebels",
            "url": "https://www.nytimes.com/2014/07/07/world/europe/ukraine-military-finds-its-footing-against-pro-russian-rebels.html",
            "published_date": "2014-07-07T01:26:34+0000",
            "category": "World",
            "abstract": "Since President Petro O. Poroshenko called off a cease-fire and ordered troops to end the rebellion, an entirely different Ukrainian military appeared at the front.",
            "image_url": "https://www.nytimes.com/images/2014/07/07/world/europe/07MILITARY/07MILITARY-articleLarge.jpg"
        },
        {
            "title": "Q. and A.: Julia Middleton and Ronald Arculli on Cultural Intelligence in a Global Era",
            "url": "https://sinosphere.blogs.nytimes.com/2014/07/07/q-and-a-julia-middleton-and-ronald-arculli-on-cultural-intelligence-in-a-global-era/",
            "published_date": "2014-07-07T07:55:00+0000",
            "category": "World",
            "abstract": "Who will lead the world to a better future? Julia Middleton\u2019s new book, \u201cCultural Intelligence,\u201d proposes the idea that people who can truly bridge cultures, in a fundamental, not superficial, way, will be the best leaders.",
            "image_url": null
        },
        {
            "title": "Lawyer Charged After Trying to Defend June 4 Commemorators",
            "url": "https://sinosphere.blogs.nytimes.com/2014/07/07/lawyer-charged-after-trying-to-defend-june-4-commemorators/",
            "published_date": "2014-07-07T08:23:25+0000",
            "category": "World",
            "abstract": "A public interest lawyer, Chang Boyang, has been charged with \u201csuspicion of illegal commercial activities\u201d after attempting to defend several attendees at a meeting discussing the 1989 Tiananmen democracy movement, lawyers said.",
            "image_url": null
        },
        {
            "title": "Xi Condemns Efforts to Play Down Japan\u2019s Wartime Aggression",
            "url": "https://sinosphere.blogs.nytimes.com/2014/07/07/xi-condemns-efforts-to-play-down-japans-wartime-aggression/",
            "published_date": "2014-07-07T09:07:07+0000",
            "category": "World",
            "abstract": "The Chinese leader warns Japan against revising history as tensions fester between the two Asian powers.",
            "image_url": null
        },
        {
            "title": "Britain to Investigate Allegations of Sexual Abuse Cover-Up Decades Ago",
            "url": "https://www.nytimes.com/2014/07/08/world/europe/britain-to-investigate-allegations-of-sexual-abuse-cover-up-decades-ago.html",
            "published_date": "2014-07-07T10:12:43+0000",
            "category": "World",
            "abstract": "The investigations follow reports that scores of documents relating to child abuse in official circles went missing at the Home Office in the 1980s.",
            "image_url": "https://www.nytimes.com/images/2014/07/08/world/08BRITAIN/08BRITAIN-articleLarge.jpg"
        }
    ],
    "2014-07-08": [
        {
            "title": "No Signs of Fabrication in Imprisoned Al Jazeera Crew\u2019s Reports From Egypt",
            "url": "https://www.nytimes.com/2014/07/08/world/middleeast/no-signs-of-fabrication-in-imprisoned-al-jazeera-crews-reports-from-egypt.html",
            "published_date": "2014-07-08T00:51:45+0000",
            "category": "World",
            "abstract": "The three journalists were recently sentenced to at least seven years in prison for spreading \u201cfalse news\u201d during their reporting on unrest in Cairo.",
            "image_url": null
        },
        {
            "title": "Opposition Rally in Nairobi",
            "url": "https://www.nytimes.com/video/world/africa/100000002985109/opposition-rally-in-nairobi.html",
            "published_date": "2014-07-08T01:41:59+0000",
            "category": "World",
            "abstract": "Opposition supporters gathered for a rally in Nairobi.",
            "image_url": "https://www.nytimes.com/images/2014/07/07/multimedia/kenya-protests/kenya-protests-articleLarge.jpg"
        },
        {
            "title": "Opposition Rallies Its Ranks in Kenya, Peacefully",
            "url": "https://www.nytimes.com/2014/07/08/world/africa/opposition-rallies-ranks-in-kenya-peacefully.html",
            "published_date": "2014-07-08T02:12:31+0000",
            "category": "World",
            "abstract": "Kenya\u2019s opposition leaders accused the government of playing tribal politics, being numb to poverty and being caught flat-footed by terrorist attacks.",
            "image_url": "https://www.nytimes.com/images/2014/07/08/world/KENYA/KENYA-articleLarge.jpg"
        },
        {
            "title": "Aid Elusive, Crimea Farms Face Hurdles",
            "url": "https://www.nytimes.com/2014/07/08/world/europe/aid-elusive-crimea-farms-face-hurdles.html",
            "published_date": "2014-07-08T02:12:33+0000",
            "category": "World",
            "abstract": "The political crisis in Crimea has disrupted multiple aspects of farming there, and the help Russia pledged after it annexed the territory has been spotty at best.",
            "image_url": "https://www.nytimes.com/images/2014/07/08/world/CRIMEA/CRIMEA-articleLarge.jpg"
        },
        {
            "title": "Q. and A.: John Delury on Chinese-South Korean Ties",
            "url": "https://sinosphere.blogs.nytimes.com/2014/07/07/q-and-a-john-delury-on-chinese-south-korean-ties/",
            "published_date": "2014-07-08T02:21:12+0000",
            "category": "World",
            "abstract": "John Delury, an assistant professor of Chinese and East Asian Studies at Yonsei University in Seoul, discusses the visit to Seoul by President Xi Jinping of China and the implications it will have on ties between South Korea and China.",
            "image_url": "https://www.nytimes.com/images/2014/07/07/world/07sino-Delury01/07sino-Delury01-articleLarge.jpg"
        }
    ],
    "2014-07-09": [
        {
            "title": "Umaru Dikko, Ex-Nigerian Official Who Was Almost Kidnapped, Dies",
            "url": "https://www.nytimes.com/2014/07/08/world/africa/umaru-dikko-ex-nigerian-official-who-was-almost-kidnapped-dies.html",
            "published_date": "2014-07-09T00:19:23+0000",
            "category": "World",
            "abstract": "In 1984, Mr. Dikko was found in a shipping crate at a London airport along with three kidnappers who had planned to ship him back to Lagos to stand trial.",
            "image_url": "https://www.nytimes.com/images/2014/07/09/world/DIKKO-obit/DIKKO-obit-articleLarge.jpg"
        },
        {
            "title": "\u2018Cutting the Grass\u2019 of Hamas\u2019s Militancy",
            "url": "https://www.nytimes.com/video/world/middleeast/100000002989054/cutting-the-grass-of-hamass-militancy.html",
            "published_date": "2014-07-09T01:22:44+0000",
            "category": "World",
            "abstract": "How Israel\u2019s latest airstrikes on Gaza are seen as part of a broader tactic known as \u201ccutting the grass,\u201d or using military incursions to manage conflict.",
            "image_url": "https://www.nytimes.com/images/2014/07/08/multimedia/nytm-cutting-grass/nytm-cutting-grass-articleLarge.jpg"
        },
        {
            "title": "NATO Chief Expresses Support for Ukraine",
            "url": "https://www.nytimes.com/video/world/europe/100000002988592/nato-chief-expresses-support-for-ukraine.html",
            "published_date": "2014-07-09T01:36:07+0000",
            "category": "World",
            "abstract": "The NATO secretary general, Anders Fogh Rasmussen, spoke about the Ukraine crisis after meeting with President Obama.",
            "image_url": "https://www.nytimes.com/images/2014/07/08/multimedia/obama-rasmussen/obama-rasmussen-articleLarge.jpg"
        },
        {
            "title": "With Talks Uncertain, Ukrainian Rebels Cling to Hope in Strongholds",
            "url": "https://www.nytimes.com/2014/07/09/world/europe/with-talks-uncertain-ukrainian-rebels-cling-to-hope-in-strongholds.html",
            "published_date": "2014-07-09T01:36:55+0000",
            "category": "World",
            "abstract": "In Donetsk, the eastern regional capital, fighters say they expect a final showdown with government troops soon.",
            "image_url": "https://www.nytimes.com/images/2014/07/09/world/UKRAINE/UKRAINE-articleLarge.jpg"
        },
        {
            "title": "Iran Sends 3 Attack Planes to Iraqi Government",
            "url": "https://www.nytimes.com/2014/07/09/world/middleeast/iran-sends-3-attack-planes-to-iraqi-government.html",
            "published_date": "2014-07-09T01:54:23+0000",
            "category": "World",
            "abstract": "Delivery of the Su-25 aircraft is the latest step Iran has taken to help Prime Minister Nuri Kamal al-Maliki battle the forces of the Islamic State in Iraq and Syria.",
            "image_url": "https://www.nytimes.com/images/2014/07/09/world/IRAN/IRAN-articleLarge.jpg"
        }
    ],
    "2014-07-10": [
        {
            "title": "Fleeing Gangs, Children Head to U.S. Border",
            "url": "https://www.nytimes.com/2014/07/10/world/americas/fleeing-gangs-children-head-to-us-border.html",
            "published_date": "2014-07-10T00:52:31+0000",
            "category": "World",
            "abstract": "An increase in gang-related killings of children is a key factor driving the surge of migration of young Central Americans to the United States.",
            "image_url": "https://www.nytimes.com/images/2014/07/10/world/HONDURAS/HONDURAS-articleLarge.jpg"
        },
        {
            "title": "A Harsh Climate Calls for Banishment of the Needy",
            "url": "https://www.nytimes.com/2014/07/10/world/europe/a-harsh-climate-calls-for-banishment-of-the-needy.html",
            "published_date": "2014-07-10T01:05:56+0000",
            "category": "World",
            "abstract": "While the rest of Norway has generous welfare programs, in the frigid territory of Svalbard, unemployment and homelessness are illegal, which officials say reduces crime.",
            "image_url": "https://www.nytimes.com/images/2014/07/10/world/NORWAY/NORWAY-articleLarge.jpg"
        },
        {
            "title": "Chinese Hackers Pursue Key Data on U.S. Workers",
            "url": "https://www.nytimes.com/2014/07/10/world/asia/chinese-hackers-pursue-key-data-on-us-workers.html",
            "published_date": "2014-07-10T01:24:27+0000",
            "category": "World",
            "abstract": "It is not yet clear how far the hackers penetrated the systems of the Office of Personnel Management, in which applicants for security clearances list their personal information.",
            "image_url": null
        },
        {
            "title": "Brazilians Grumble and Take Stock After Crushing World Cup Loss",
            "url": "https://www.nytimes.com/2014/07/10/world/americas/humiliation-and-heartbreak-brazil-processes-the-unthinkable.html",
            "published_date": "2014-07-10T01:38:31+0000",
            "category": "World",
            "abstract": "While the hope was to blot out the bad memory of the last time the country hosted the World Cup, the outcome was if anything worse. But in a more mature Brazil, people are asking whether it will matter as much.",
            "image_url": null
        },
        {
            "title": "Patchwork Makeup of Rebels Fighting Ukraine Makes Peace Talks Elusive",
            "url": "https://www.nytimes.com/2014/07/10/world/europe/patchwork-makeup-of-rebels-fighting-ukraine-makes-peace-talks-elusive.html",
            "published_date": "2014-07-10T01:52:41+0000",
            "category": "World",
            "abstract": "One Russian separatist leader is said to be trying to unite the mishmash of militias into a single professional fighting force, while the national military prepares to attempt to retake the rebel stronghold of Donetsk.",
            "image_url": null
        }
    ],
    "2014-07-11": [
        {
            "title": "Q. and A.: Rana Mitter on the Legacy of World War II in Asia",
            "url": "https://sinosphere.blogs.nytimes.com/2014/07/10/q-and-a-rana-mitter-on-world-war-iis-legacy-in-asia/",
            "published_date": "2014-07-11T00:08:20+0000",
            "category": "World",
            "abstract": "The Oxford historian says that, unlike in Europe, where a broad consensus on the war has been achieved, interpretations of the conflict in Asia remain a source of acrimony between the major players, with important ramifications for the future of the region.",
            "image_url": "https://www.nytimes.com/images/2014/07/10/blogs/10sino-Mitter01/10sino-Mitter01-articleLarge.jpg"
        },
        {
            "title": "Grim Search on a Gaza Beach",
            "url": "https://www.nytimes.com/video/world/middleeast/100000002994121/grim-search-on-a-gaza-beach.html",
            "published_date": "2014-07-11T00:12:21+0000",
            "category": "World",
            "abstract": "Two brothers were among at least eight people killed by an Israeli airstrike while gathered on a Gaza beach to watch the World Cup. A third brother was missing.",
            "image_url": "https://www.nytimes.com/images/2014/07/10/multimedia/gaza-cafe/gaza-cafe-articleLarge.jpg"
        },
        {
            "title": "U.N. Proposal Fails to Ease Crisis Over Disputed Afghan Election",
            "url": "https://www.nytimes.com/2014/07/11/world/asia/un-proposal-fails-to-ease-crisis-over-disputed-afghan-election.html",
            "published_date": "2014-07-11T00:38:11+0000",
            "category": "World",
            "abstract": "The proposal, centering on a special audit of suspected fraudulent votes, appeared to waver nearly as quickly as it was proposed.",
            "image_url": null
        },
        {
            "title": "New Envoy for Syria Appointed",
            "url": "https://www.nytimes.com/2014/07/11/world/new-envoy-for-syria-appointed.html",
            "published_date": "2014-07-11T01:14:14+0000",
            "category": "World",
            "abstract": "Secretary General Ban Ki-moon announced Thursday that he had appointed Staffan de Mistura, a veteran diplomat of Italian-Swedish heritage, to be the new special envoy responsible for seeking an end to the conflict in Syria.",
            "image_url": null
        },
        {
            "title": "Bahrain: Opposition Under Fire",
            "url": "https://www.nytimes.com/2014/07/11/world/middleeast/bahrain-opposition-under-fire.html",
            "published_date": "2014-07-11T01:16:17+0000",
            "category": "World",
            "abstract": "The government charged two leaders of Bahrain\u2019s largest opposition group with illegally meeting an American official.",
            "image_url": null
        }
    ],
    "2014-07-12": [
        {
            "title": "Guiding Germany\u2019s Young Muslims Off the Road to Jihad",
            "url": "https://www.nytimes.com/2014/07/12/world/europe/guiding-germanys-young-muslims-off-the-road-to-jihad.html",
            "published_date": "2014-07-12T00:04:18+0000",
            "category": "World",
            "abstract": "Claudia Dantschke, whose East German upbringing fostered a thirst for things foreign, has gained a growing role in Germany\u2019s response to radical Islam.",
            "image_url": "https://www.nytimes.com/images/2014/07/12/world/12CLAUDIA/12CLAUDIA-articleLarge.jpg"
        },
        {
            "title": "Turkey: Prime Minister Looks Ahead",
            "url": "https://www.nytimes.com/2014/07/12/world/europe/turkey-prime-minister-looks-ahead.html",
            "published_date": "2014-07-12T00:23:02+0000",
            "category": "World",
            "abstract": "Prime Minister Recep Tayyip Erdogan outlined his vision for his presidential campaign, promising to expand rights and liberties, improve welfare programs and build up the country\u2019s economy.",
            "image_url": null
        },
        {
            "title": "South Sudan: Refugee Crisis Worsens",
            "url": "https://www.nytimes.com/2014/07/12/world/africa/south-sudan-refugee-crisis-worsens.html",
            "published_date": "2014-07-12T00:26:04+0000",
            "category": "World",
            "abstract": "The number of South Sudanese fleeing for neighboring nations has reached 715,000, the United Nations refugee agency said, amid a civil war and the threat of famine.",
            "image_url": null
        },
        {
            "title": "U.S. Knew Britain Planned to Erase Data at The Guardian",
            "url": "https://www.nytimes.com/2014/07/12/world/europe/us-knew-britain-planned-to-erase-data-at-the-guardian.html",
            "published_date": "2014-07-12T01:02:18+0000",
            "category": "World",
            "abstract": "After Britain forced The Guardian to destroy hard drives holding data leaked by Edward J. Snowden, a National Security Agency official called the event \u201cgood news,\u201d emails show.",
            "image_url": "https://www.nytimes.com/images/2014/07/12/world/GUARDIAN-1/GUARDIAN-1-articleLarge.jpg"
        },
        {
            "title": "Mideast Rockets and Airstrikes Continue",
            "url": "https://www.nytimes.com/video/world/100000002996256/mideast-rockets-and-airstrikes-continue.html",
            "published_date": "2014-07-12T01:08:51+0000",
            "category": "World",
            "abstract": "Gazans and Israelis braced for further conflict as Hamas fired more rockets into Israel and Israel continued its aerial assaults on Gaza.",
            "image_url": "https://www.nytimes.com/images/2014/07/11/multimedia/israel-gaza-conflict/israel-gaza-conflict-articleLarge.jpg"
        }
    ],
    "2014-07-13": [
        {
            "title": "Putin and Argentine Leader Agree on Nuclear Power Project",
            "url": "https://www.nytimes.com/2014/07/13/world/americas/putin-and-argentine-leader-agree-on-nuclear-power-project.html",
            "published_date": "2014-07-13T00:17:37+0000",
            "category": "World",
            "abstract": "The Russian president and President Cristina Fern\u00e1ndez de Kirchner also discussed cooperation on military technology and satellites.",
            "image_url": null
        },
        {
            "title": "The Growing Reach of Hamas\u2019s Rockets",
            "url": "https://www.nytimes.com/interactive/2014/07/13/world/middleeast/the-growing-reach-of-hamas-rockets.html",
            "published_date": "2014-07-13T05:36:06+0000",
            "category": "World",
            "abstract": "How the range of Hamas\u2019s rockets has expanded since 2001.",
            "image_url": "https://www.nytimes.com/images/2014/07/13/world/middleeast/the-growing-reach-of-hamas-rockets-1405229117556/the-growing-reach-of-hamas-rockets-1405229117556-articleLarge.jpg"
        },
        {
            "title": "1914: Brady Climbs The M\u00f6nch in Just Ten Hours",
            "url": "https://iht-retrospective.blogs.nytimes.com/2014/07/13/1914-brady-climbs-the-monch-in-just-ten-hours/",
            "published_date": "2014-07-13T09:43:17+0000",
            "category": "World",
            "abstract": "Highlights from the International Herald Tribune archives: a perilous ascent in Switzerland in 1914 by Mr. J. H. Brady.",
            "image_url": "https://www.nytimes.com/images/2014/07/14/blogs/14iht-old14-monch/14iht-old14-monch-articleLarge.png"
        },
        {
            "title": "Palestinians Flee Northern Gaza as a Cease-Fire Appears Elusive",
            "url": "https://www.nytimes.com/2014/07/14/world/middleeast/israel-gaza.html",
            "published_date": "2014-07-13T13:09:34+0000",
            "category": "World",
            "abstract": "Israel\u2019s aerial bombardment of Gaza continued Sunday, as did rocket fire into Israel, as Israeli leaders and Palestinian militants both appeared ready to continue and escalate the conflict.",
            "image_url": "https://www.nytimes.com/images/2014/07/13/world/middleeast/14GAZA3/14GAZA3-articleLarge.jpg"
        },
        {
            "title": "1939: England Bans Revengeful Wills",
            "url": "https://iht-retrospective.blogs.nytimes.com/2014/07/13/1939-england-bans-revengeful-wills/",
            "published_date": "2014-07-13T15:44:39+0000",
            "category": "World",
            "abstract": "Highlights from the International Herald Tribune archives: New bill in England bans revengeful wills in 1939.",
            "image_url": null
        }
    ],
    "2014-07-14": [
        {
            "title": "For a Weekend, Ukraine Rebels Make Love, Not War",
            "url": "https://www.nytimes.com/2014/07/14/world/europe/first-self-declared-wedding-in-donetsk-peoples-republic-ukraine-rebels-make-love-not-war.html",
            "published_date": "2014-07-14T00:54:47+0000",
            "category": "World",
            "abstract": "A wedding was billed as the first in the self-declared Donetsk People\u2019s Republic, and on Saturday it was singles night.",
            "image_url": "https://www.nytimes.com/images/2014/07/14/world/WEDDING/WEDDING-articleLarge.jpg"
        },
        {
            "title": "Jerusalem\u2019s Damaged Link",
            "url": "https://www.nytimes.com/video/world/middleeast/100000002998159/jerusalems-damaged-link.html",
            "published_date": "2014-07-14T01:29:30+0000",
            "category": "World",
            "abstract": "A light rail line connecting Arab and Jewish neighborhoods in Jerusalem was damaged during riots. Some Arab residents would rather not see the line re-opened.",
            "image_url": "https://www.nytimes.com/images/2014/07/13/multimedia/israel-jerusalem-rail/israel-jerusalem-rail-articleLarge.jpg"
        },
        {
            "title": "Grief and Evacuation in Gaza",
            "url": "https://www.nytimes.com/slideshow/2014/07/14/world/middleeast/20140714-GAZA.html",
            "published_date": "2014-07-14T01:47:25+0000",
            "category": "World",
            "abstract": "As 18 victims of an airstrike in Gaza City were buried, Palestinians fled the north after Israel warned of major attacks.",
            "image_url": "https://www.nytimes.com/images/2014/07/14/world/middleeast/20140714-GAZA-slide-9ABR/20140714-GAZA-slide-9ABR-articleLarge.jpg"
        },
        {
            "title": "U.S. Sees Risks in Assisting a Compromised Iraqi Force",
            "url": "https://www.nytimes.com/2014/07/14/world/middleeast/us-sees-risks-in-assisting-a-compromised-iraqi-force.html",
            "published_date": "2014-07-14T01:52:31+0000",
            "category": "World",
            "abstract": "A classified report says that many units are deeply infiltrated by either Sunni extremist informants or Shiite personnel backed by Iran, according to U.S. officials.",
            "image_url": "https://www.nytimes.com/images/2014/07/14/world/MILITARY/MILITARY-articleLarge.jpg"
        },
        {
            "title": "In Divided Jerusalem, Rail Line for Arabs and Jews Is Among the Fractures",
            "url": "https://www.nytimes.com/2014/07/14/world/middleeast/in-divided-jerusalem-rail-line-for-arabs-and-jews-is-among-the-fractures.html",
            "published_date": "2014-07-14T01:54:27+0000",
            "category": "World",
            "abstract": "Rioters in a Palestinian neighborhood in Jerusalem destroyed two light-rail stations, breaking what some saw as an artery of coexistence in a city that is otherwise split.",
            "image_url": null
        }
    ],
    "2014-07-15": [
        {
            "title": "Ukrainian Military Plane Is Shot Down as Russia Adds to Presence at Border",
            "url": "https://www.nytimes.com/2014/07/15/world/europe/ukrainian-military-plane-is-shot-down-as-russia-adds-to-presence-at-border.html",
            "published_date": "2014-07-15T00:59:51+0000",
            "category": "World",
            "abstract": "Although the details have yet to be verified, a spokeswoman for a separatist group said rebels had taken five members of the plane\u2019s crew as hostages.",
            "image_url": "https://www.nytimes.com/images/2014/07/15/world/UKRAINE/UKRAINE-articleLarge.jpg"
        },
        {
            "title": "British Foreign Secretary Quits for Lower Position in the Cabinet",
            "url": "https://www.nytimes.com/2014/07/15/world/europe/william-hague-resigns-as-britains-foreign-secretary.html",
            "published_date": "2014-07-15T01:07:50+0000",
            "category": "World",
            "abstract": "The resignation of William Hague was a surprise in Prime Minister David Cameron\u2019s government shuffle.",
            "image_url": "https://www.nytimes.com/images/2014/07/15/world/15HAGUE-1/15HAGUE-1-articleLarge.jpg"
        },
        {
            "title": "Gaza Families Near Israeli Border Struggle to Build a Life in the Heart of a Conflict",
            "url": "https://www.nytimes.com/2014/07/15/world/middleeast/gaza-families-near-israeli-border-struggle-to-build-a-life-in-the-heart-of-a-conflict.html",
            "published_date": "2014-07-15T01:26:56+0000",
            "category": "World",
            "abstract": "Thousands of Palestinian families have fled, some several times, during years of fighting in the Palestinian coastal territory.",
            "image_url": "https://www.nytimes.com/images/2014/07/15/world/SCENE/SCENE-articleLarge.jpg"
        },
        {
            "title": "Anxious Moments for an Afghanistan on the Brink",
            "url": "https://www.nytimes.com/2014/07/15/world/asia/anxious-moments-for-an-afghanistan-on-the-brink.html",
            "published_date": "2014-07-15T01:52:08+0000",
            "category": "World",
            "abstract": "The aftermath of the presidential runoff included as tumultuous a six-day stretch for Afghanistan as any since the American invasion in 2001.",
            "image_url": "https://www.nytimes.com/images/2014/07/15/world/AFGHANISTAN/AFGHANISTAN-articleLarge.jpg"
        },
        {
            "title": "Iran Outlines Nuclear Deal; Accepts Limit",
            "url": "https://www.nytimes.com/2014/07/15/world/middleeast/iran-outlines-nuclear-deal-accepts-limit.html",
            "published_date": "2014-07-15T02:06:54+0000",
            "category": "World",
            "abstract": "Iran\u2019s foreign minister, Mohammad Javad Zarif, said the country could accept a freeze on its capacity to produce nuclear fuel at current levels for several years, provided it could eventually produce fuel unhindered.",
            "image_url": "https://www.nytimes.com/images/2014/07/15/world/NUKES/NUKES-articleLarge-v2.jpg"
        }
    ],
    "2014-07-16": [
        {
            "title": "Whisked Away for Tea With a Rebel in Ukraine",
            "url": "https://www.nytimes.com/2014/07/16/world/europe/whisked-away-for-tea-with-a-rebel-in-ukraine.html",
            "published_date": "2014-07-16T00:36:59+0000",
            "category": "World",
            "abstract": "A New York Times reporter was stopped at a checkpoint and then driven off for an unusual inquiry into her credentials.",
            "image_url": null
        },
        {
            "title": "Transit Cards to Replace Cash on Kenyan Minibuses Are a Hard Sell",
            "url": "https://www.nytimes.com/2014/07/16/world/africa/transit-cards-to-replace-cash-on-kenyan-minibuses-a-hard-sell.html",
            "published_date": "2014-07-16T00:58:09+0000",
            "category": "World",
            "abstract": "Though the cashless payment system being pushed by Google would make it easier for the government to collect millions of dollars in taxes, many have resisted the change.",
            "image_url": null
        },
        {
            "title": "Take a Wild Ride on Kenya\u2019s Minibuses",
            "url": "https://www.nytimes.com/video/world/africa/100000003001947/cash-only-for-nairobis-matatus.html",
            "published_date": "2014-07-16T01:01:55+0000",
            "category": "World",
            "abstract": "Jeffrey Gettleman rides on the unregulated minibuses that are fighting a move toward electronic payments.",
            "image_url": "https://www.nytimes.com/images/2014/07/15/multimedia/kenya-matatu-economy/kenya-matatu-economy-articleLarge.jpg"
        },
        {
            "title": "A Canadian\u2019s Pitch for ISIS",
            "url": "https://www.nytimes.com/video/world/middleeast/100000003001205/a-canadians-pitch-for-isis.html",
            "published_date": "2014-07-16T01:23:18+0000",
            "category": "World",
            "abstract": "Al-Hayat Media Center, an affiliate of the Islamic State in Iraq and Syria that offers mostly non-Arabic material geared toward Westerners, released a video featuring a \u201cmartyred\u201d Canadian.",
            "image_url": "https://www.nytimes.com/images/2014/07/15/multimedia/isis-recruit/isis-recruit-articleLarge.jpg"
        },
        {
            "title": "Canadian Killed in Syria Lives On as Pitchman for Jihadis",
            "url": "https://www.nytimes.com/2014/07/16/world/middleeast/isis-uses-andre-poulin-a-canadian-convert-to-islam-in-recruitment-video.html",
            "published_date": "2014-07-16T01:27:30+0000",
            "category": "World",
            "abstract": "ISIS, the militant group that controls large parts of Iraq and Syria, has distributed a recruiting video using Andre Poulin, a Canadian who converted to Islam and later died in battle.",
            "image_url": null
        }
    ],
    "2014-07-17": [
        {
            "title": "President Obama on Middle East Fighting",
            "url": "https://www.nytimes.com/video/world/middleeast/100000003004954/president-obama-on-middle-east-fighting.html",
            "published_date": "2014-07-17T00:36:52+0000",
            "category": "World",
            "abstract": "At an appearance at the White House, the president discussed the ongoing conflict between Israelis and Palestinians.",
            "image_url": "https://www.nytimes.com/images/2014/07/17/us/SANCTIONS/SANCTIONS-articleLarge.jpg"
        },
        {
            "title": "For Iraq, Debacle in Tikrit as Forces Walk Into Trap Set by Militants",
            "url": "https://www.nytimes.com/2014/07/17/world/middleeast/for-iraq-debacle-in-tikrit-as-forces-walk-into-trap-set-by-militants.html",
            "published_date": "2014-07-17T00:45:31+0000",
            "category": "World",
            "abstract": "Scores of soldiers \u2014 and even more of their untrained volunteer supporters \u2014 were either killed or badly wounded when the Islamic State in Iraq and Syria attacked.",
            "image_url": null
        },
        {
            "title": "Through Lens, 4 Boys Dead by Gaza Shore",
            "url": "https://www.nytimes.com/2014/07/17/world/middleeast/through-lens-4-boys-dead-by-gaza-shore.html",
            "published_date": "2014-07-17T00:56:22+0000",
            "category": "World",
            "abstract": "A New York Times photographer gives his account of explosions and sudden death.",
            "image_url": "https://www.nytimes.com/images/2014/07/17/world/07GAZA-1/07GAZA-1-articleLarge.jpg"
        },
        {
            "title": "Obama Likely to Seek Additional Time for Nuclear Negotiations With Iran",
            "url": "https://www.nytimes.com/2014/07/17/world/middleeast/obama-likely-to-seek-additional-time-for-nuclear-negotiations-with-iran.html",
            "published_date": "2014-07-17T01:04:52+0000",
            "category": "World",
            "abstract": "Iran has signaled that it wants more time to negotiate past Sunday\u2019s deadline, but the president is almost certain to run into congressional opposition if he agrees.",
            "image_url": null
        },
        {
            "title": "Questions of Justice in Tunisia as Ousted Leaders Are Freed",
            "url": "https://www.nytimes.com/2014/07/17/world/africa/questions-of-justice-in-tunisia-as-ousted-leaders-are-freed.html",
            "published_date": "2014-07-17T01:36:04+0000",
            "category": "World",
            "abstract": "Most of the senior officials of Tunisia\u2019s former government have been released from prison, raising accusations of injustice from relatives of victims and human rights activists in the wake of the 2011 Arab Spring uprising.",
            "image_url": "https://www.nytimes.com/images/2014/07/17/world/TUNIS-2/TUNIS-2-articleLarge.jpg"
        }
    ],
    "2014-07-18": [
        {
            "title": "From Gaza, an Array of Makeshift Rockets Packs a Counterpunch",
            "url": "https://www.nytimes.com/2014/07/18/world/middleeast/from-gaza-an-array-of-makeshift-rockets-packs-a-counterpunch.html",
            "published_date": "2014-07-18T00:22:51+0000",
            "category": "World",
            "abstract": "Though the crude rockets smuggled from Iran, Libya, Sudan and Syria rarely hit high-value targets, they are reaching farther into Israel than ever before.",
            "image_url": "https://www.nytimes.com/images/2014/07/18/world/ROCKETS/ROCKETS-articleLarge.jpg"
        },
        {
            "title": "Egypt Cuts Tax Breaks for Fuel; Few Protest",
            "url": "https://www.nytimes.com/2014/07/18/world/middleeast/egypt-cuts-tax-breaks-for-fuel-few-protest.html",
            "published_date": "2014-07-18T00:26:58+0000",
            "category": "World",
            "abstract": "Critics say that President Abdel Fattah el-Sisi call for a drastic cut to energy subsidies in order to decrease the country\u2019s budget deficit will harm vulnerable citizens.",
            "image_url": "https://www.nytimes.com/images/2014/07/18/world/EGYPT/EGYPT-articleLarge.jpg"
        },
        {
            "title": "Air Disaster Strains Moscow\u2019s Competing Strategy on Ukrainian Rebels",
            "url": "https://www.nytimes.com/2014/07/18/world/europe/air-disaster-strains-moscows-competing-strategy-on-ukrainian-rebels.html",
            "published_date": "2014-07-18T00:36:16+0000",
            "category": "World",
            "abstract": "The Kremlin\u2019s double game in Ukraine \u2014 publicly endorsing peace talks while secretly supporting the separatists \u2014 appeared less crafty than disastrous after the downing of a Malaysian jet.",
            "image_url": "https://www.nytimes.com/images/2014/07/18/world/RUSSIA/RUSSIA-articleLarge.jpg"
        },
        {
            "title": "Germany: American Spy Chief Leaves",
            "url": "https://www.nytimes.com/2014/07/18/world/europe/germany-american-spy-chief-leaves.html",
            "published_date": "2014-07-18T00:40:34+0000",
            "category": "World",
            "abstract": "The United States\u2019 top spy in Germany has left the country, the American Embassy in Berlin said Thursday, a week after Germany demanded that the C.I.A.\u2019s Berlin station chief leave.",
            "image_url": null
        },
        {
            "title": "Tragedy on Top of Crisis May Strengthen Stand Against Russia in U.S. and Europe",
            "url": "https://www.nytimes.com/2014/07/18/world/europe/tragedy-on-top-of-crisis-may-strengthen-stand-against-russia-in-us-and-europe.html",
            "published_date": "2014-07-18T01:08:41+0000",
            "category": "World",
            "abstract": "If the Malaysia Airlines jet was downed by pro-Russian separatists, it will reinforce the United States\u2019 urging for a stronger stance against Moscow.",
            "image_url": "https://www.nytimes.com/images/2014/07/18/world/DIPLO/DIPLO-articleLarge.jpg"
        }
    ],
    "2014-07-19": [
        {
            "title": "Ethiopia: Bloggers and Journalists Are Charged as Terrorists",
            "url": "https://www.nytimes.com/2014/07/19/world/africa/ethiopia-bloggers-and-journalists-are-charged-as-terrorists.html",
            "published_date": "2014-07-19T00:05:05+0000",
            "category": "World",
            "abstract": "Three Ethiopian journalists and six bloggers were charged with planning terrorist attacks during a court hearing in Addis Ababa on Friday morning, nearly three months after they were arrested.",
            "image_url": null
        },
        {
            "title": "NBC Correspondent Ayman Mohyeldin Is Returned to Gaza",
            "url": "https://www.nytimes.com/2014/07/19/business/media/nbc-correspondent-ayman-mohyeldin-is-returned-to-gaza.html",
            "published_date": "2014-07-19T00:10:16+0000",
            "category": "Business Day",
            "abstract": "Ayman Mohyeldin was reinstated by the network after he was removed following postings on Twitter that stirred controversy, although NBC did not make any public comment.",
            "image_url": null
        },
        {
            "title": "Israel Ready to Expand Ground Forces",
            "url": "https://www.nytimes.com/video/world/middleeast/100000003009157/israel-ready-to-expand-ground-forces.html",
            "published_date": "2014-07-19T00:29:34+0000",
            "category": "World",
            "abstract": "Prime Minister Benjamin Netanyahu of Israel said Friday that the Israeli military was ready for a \u201csignificant expansion\u201d of ground forces in Gaza.",
            "image_url": "https://www.nytimes.com/images/2014/07/18/multimedia/netanyahu-expansion/netanyahu-expansion-articleLarge-v2.jpg"
        },
        {
            "title": "ISIS Forces Last Iraqi Christians to Flee Mosul",
            "url": "https://www.nytimes.com/2014/07/19/world/middleeast/isis-forces-last-iraqi-christians-to-flee-mosul.html",
            "published_date": "2014-07-19T00:39:17+0000",
            "category": "World",
            "abstract": "An era of tolerance for different religions appeared to have come to an abrupt end as minority sects sought sanctuary from militants in Christian enclaves.",
            "image_url": "https://www.nytimes.com/images/2014/07/19/world/IRAQ01/IRAQ01-articleLarge.jpg"
        },
        {
            "title": "Downing of Jet Exposes Defects of Flight Precautions Over Ukraine",
            "url": "https://www.nytimes.com/2014/07/19/world/europe/downing-of-plane-exposes-defects-of-flight-precautions-over-ukraine.html",
            "published_date": "2014-07-19T01:06:28+0000",
            "category": "World",
            "abstract": "Flight restrictions underestimated the risks to a startling degree, leaving Flight 17 exposed at 33,000 feet to missiles known to fly to more than twice that height.",
            "image_url": "https://www.nytimes.com/images/2014/07/19/world/FLIGHT/FLIGHT-articleLarge.jpg"
        }
    ],
    "2014-07-20": [
        {
            "title": "In Hospitals Across Gaza, Scenes of Chaos and Grief",
            "url": "https://www.nytimes.com/2014/07/20/world/middleeast/gaza-poorly-equipped-hospitals-before-israeli-military-operation-now-scenes-of-chaos-and-grief.html",
            "published_date": "2014-07-20T03:22:57+0000",
            "category": "World",
            "abstract": "Hospitals that were poorly equipped and staffed even before the Israeli military operation are struggling to cope with a surge of casualties from a war that continues to intensify.",
            "image_url": "https://www.nytimes.com/images/2014/07/20/world/20HOSPITAL/20HOSPITAL-articleLarge.jpg"
        },
        {
            "title": "Neighborhood Ravaged on Deadliest Day So Far for Both Sides in Gaza",
            "url": "https://www.nytimes.com/2014/07/21/world/middleeast/gaza-israel.html",
            "published_date": "2014-07-20T08:38:54+0000",
            "category": "World",
            "abstract": "The withering assault on the neighborhood of Shejaiya, and the death of 87 Palestinians and 13 Israeli soldiers and officers, appeared to shake the international community.",
            "image_url": null
        },
        {
            "title": "As Anger Rises Over Crash, Malaysian Government Is Reluctant to Assign Blame",
            "url": "https://www.nytimes.com/2014/07/21/world/asia/as-anger-rises-over-crash-malaysian-government-is-reluctant-to-assign-blame.html",
            "published_date": "2014-07-20T10:27:55+0000",
            "category": "World",
            "abstract": "Officials have so far avoided joining the United States and many other countries in openly attributing the disaster to the Russian government.",
            "image_url": null
        },
        {
            "title": "Bodies From Malaysia Airlines Flight Are Stuck in Ukraine, Held Hostage Over Distrust",
            "url": "https://www.nytimes.com/2014/07/21/world/europe/malaysia-airlines-jet-ukraine.html",
            "published_date": "2014-07-20T11:55:17+0000",
            "category": "World",
            "abstract": "World leaders expressed a growing outrage over pro-Russian rebels\u2019 refusal to cede authority over the site where the downed jet\u2019s debris is scattered.",
            "image_url": "https://www.nytimes.com/images/2014/07/21/world/JETjp01/JETjp01-articleLarge.jpg"
        },
        {
            "title": "1889: Jack The Ripper Said to Have Connection With Police",
            "url": "https://iht-retrospective.blogs.nytimes.com/2014/07/20/1889-jack-the-ripper-said-to-have-connection-with-police/",
            "published_date": "2014-07-20T14:03:01+0000",
            "category": "World",
            "abstract": "Highlights from the International Herald Tribune archives: Jack the Ripper strikes again in London in 1889.",
            "image_url": "https://www.nytimes.com/images/2014/07/21/blogs/21iht-jackripper-art/21iht-jackripper-art-jumbo.png"
        }
    ],
    "2014-07-21": [
        {
            "title": "Mourning 3 on Jetliner Who Drew Others to Them",
            "url": "https://www.nytimes.com/2014/07/21/world/europe/teacher-and-restaurateurs-were-malaysia-airlines-flight-17-17-victims.html",
            "published_date": "2014-07-21T00:04:38+0000",
            "category": "World",
            "abstract": "Laurens van der Graaff, \u201cimpossible to dislike,\u201d became a teacher like his parents, and Jenny Loh and Shun Po Fan, whose \u201cdream was to please their guests,\u201d ran restaurants.",
            "image_url": "https://www.nytimes.com/images/2014/07/21/world/21LAURENS/21LAURENS-articleLarge.jpg"
        },
        {
            "title": "Economic Classes in Africa",
            "url": "https://www.nytimes.com/interactive/2014/07/20/world/africa/economic-classes-in-africa.html",
            "published_date": "2014-07-21T00:42:34+0000",
            "category": "World",
            "abstract": "There are more than twice as many people considered middle class in sub-Saharan Africa than there were 30 years ago. But in most countries, the poorer and richer classes grew as well, so income distributions have gone largely unchanged.",
            "image_url": "https://www.nytimes.com/images/2014/07/20/world/africa/economic-classes-in-africa-1405902645235/economic-classes-in-africa-1405902645235-articleLarge-v2.png"
        },
        {
            "title": "Africans Open Fuller Wallets to the Future",
            "url": "https://www.nytimes.com/2014/07/21/world/africa/economy-improves-as-middle-class-africans-open-wallets-to-the-future.html",
            "published_date": "2014-07-21T01:32:23+0000",
            "category": "World",
            "abstract": "Across sub-Saharan Africa, consumer demand is fueling the continent\u2019s economies in new ways, driving hopes that Africa will emerge as a success story.",
            "image_url": "https://www.nytimes.com/images/2014/07/21/world/AFRICAECON01/AFRICAECON01-articleLarge.jpg"
        },
        {
            "title": "Trying to Slow the Illegal Flow of Young Migrants",
            "url": "https://www.nytimes.com/2014/07/21/world/americas/trying-to-slow-the-illegal-flow-of-young-migrants-at-the-border-reports-show-decline-in-texas.html",
            "published_date": "2014-07-21T01:44:29+0000",
            "category": "World",
            "abstract": "Bus operators in Honduras say they are noticing a decline in the number of unaccompanied children headed to the border, and the Border Patrol has reported a dip in the number of people apprehended in Texas.",
            "image_url": "https://www.nytimes.com/images/2014/07/21/world/americas/20140721IMMIGRATION-slide-K04F/20140721IMMIGRATION-slide-K04F-articleLarge.jpg"
        },
        {
            "title": "Dutch Grief Abounds, but Mourning Stays Local",
            "url": "https://www.nytimes.com/2014/07/21/world/europe/public-mourning-declared-in-netherlands-dutch-grief-abounds-mh17-malaysia-airlines-flight-17.html",
            "published_date": "2014-07-21T01:56:08+0000",
            "category": "World",
            "abstract": "There has been no day of public mourning declared in the Netherlands for the nearly 200 citizens killed aboard Flight 17; nobody is wearing black; flags flying at half-staff are rarely seen.",
            "image_url": "https://www.nytimes.com/images/2014/07/21/world/NETHERLANDS01/NETHERLANDS01-articleLarge.jpg"
        }
    ],
    "2014-07-22": [
        {
            "title": "U.S. Mentors Prepare to Let Afghan Forces Go It Alone",
            "url": "https://www.nytimes.com/2014/07/22/world/asia/us-mentors-prepare-to-let-afghan-forces-go-it-alone.html",
            "published_date": "2014-07-22T00:20:41+0000",
            "category": "World",
            "abstract": "American Special Forces teams have been a central part of Afghanistan\u2019s security landscape, and how Afghan forces will fare after their departure will help define America\u2019s legacy in the country.",
            "image_url": null
        },
        {
            "title": "Boko Haram Rebels Seize a Town in Nigeria",
            "url": "https://www.nytimes.com/2014/07/22/world/africa/boko-haram-rebels-seize-a-town-in-nigeria.html",
            "published_date": "2014-07-22T00:27:58+0000",
            "category": "World",
            "abstract": "The takeover of Damboa was the latest defeat for a Nigerian military that has proved unable to stem repeated attacks on civilians by the group this year.",
            "image_url": null
        },
        {
            "title": "Journey Home Finally Begins for the Victims of Malaysia Airlines Flight",
            "url": "https://www.nytimes.com/2014/07/22/world/europe/train-whistle-planes-dead-begin-somber-journey-back-home-from-ukraine.html",
            "published_date": "2014-07-22T01:00:59+0000",
            "category": "World",
            "abstract": "The train bearing the bodies of the victims of Malaysia Airlines Flight 17 finally began its long journey to get them out of Ukraine\u2019s war-torn badlands and closer to home.",
            "image_url": "https://www.nytimes.com/images/2014/07/22/world/22BODIES-1/22BODIES-1-articleLarge.jpg"
        },
        {
            "title": "Corralling Carbon Before It Belches From Stack",
            "url": "https://www.nytimes.com/2014/07/22/science/corralling-carbon-before-it-belches-from-stack.html",
            "published_date": "2014-07-22T02:19:06+0000",
            "category": "Science",
            "abstract": "Many scientists say capturing the carbon that spews from power plants and locking it away is necessary to stave off the worst effects of climate change.",
            "image_url": "https://www.nytimes.com/images/2014/07/22/us/22jpCAPTURE1/22jpCAPTURE1-articleLarge.jpg"
        },
        {
            "title": "Jet Wreckage Bears Signs of Impact by Supersonic Missile, Analysis Shows",
            "url": "https://www.nytimes.com/2014/07/22/world/europe/jet-wreckage-bears-signs-of-impact-by-supersonic-missile-analysis-shows.html",
            "published_date": "2014-07-22T02:20:57+0000",
            "category": "World",
            "abstract": "A piece from the Malaysia Airlines plane in Ukraine, examined in photographs by defense consultants, had damage consistent with that from a fragmenting warhead, the kind carried by an SA-11 missile.",
            "image_url": "https://www.nytimes.com/images/2014/07/22/world/MISSILE01-copy/MISSILE01-articleLarge.jpg"
        }
    ],
    "2014-07-23": [
        {
            "title": "Fighting in Gaza Continues",
            "url": "https://www.nytimes.com/slideshow/2014/07/22/world/middleeast/20130723-ISRAEL-now.html",
            "published_date": "2014-07-23T00:23:11+0000",
            "category": "World",
            "abstract": "The Palestinian death toll rose while the Israeli military said it had struck weapons stores and other infrastructure in Gaza.",
            "image_url": "https://www.nytimes.com/images/2014/07/22/world/middleeast/20130723-ISRAEL-slide-EZBR/20130723-ISRAEL-slide-EZBR-articleLarge.jpg"
        },
        {
            "title": "Ukrainians, Awaiting International Action After Crash, Fear Complacency",
            "url": "https://www.nytimes.com/2014/07/23/world/europe/ukrainians-awaiting-international-action-after-crash-fear-complacency.html",
            "published_date": "2014-07-23T00:42:57+0000",
            "category": "World",
            "abstract": "Although the investigation into the downing of a Malaysian jetliner is in its early stages, the lack of a swift concrete response and aggressive denials by Russia have many Ukrainians worried.",
            "image_url": null
        },
        {
            "title": "Celebrities on Scottish Independence",
            "url": "https://www.nytimes.com/video/world/europe/100000002986034/celebrities-on-scottish-independence.html",
            "published_date": "2014-07-23T01:29:44+0000",
            "category": "World",
            "abstract": "Actors, authors and singers weigh in on whether or not Scotland should break away from Britain, ahead of the country\u2019s referendum in September.",
            "image_url": "https://www.nytimes.com/images/2014/07/07/world/europe/scotlandvideo2/scotlandvideo2-articleLarge.jpg"
        },
        {
            "title": "Reading the Future of Scotland in the Stars",
            "url": "https://www.nytimes.com/2014/07/23/world/europe/reading-the-future-of-scotland-in-the-stars.html",
            "published_date": "2014-07-23T01:30:30+0000",
            "category": "World",
            "abstract": "Celebrities have found that taking a stand either way on Scotland's independence referendum can stir anger in about half of its population.",
            "image_url": "https://www.nytimes.com/images/2014/07/23/world/SCOTLANDjp/SCOTLANDjp-articleLarge.jpg"
        },
        {
            "title": "Hamas Gambled on War as Its Woes Grew in Gaza",
            "url": "https://www.nytimes.com/2014/07/23/world/middleeast/hamas-gambled-on-war-as-its-woes-grew-in-gaza.html",
            "published_date": "2014-07-23T01:36:32+0000",
            "category": "World",
            "abstract": "When war between Israel and Hamas broke out two weeks ago, the Palestinian militant group was so hamstrung, politically, economically and diplomatically, that its leaders appeared to feel they had nothing to lose.",
            "image_url": "https://www.nytimes.com/images/2014/07/23/world/HAMASjp/HAMASjp-articleLarge-v2.jpg"
        }
    ],
    "2014-07-24": [
        {
            "title": "42 Are Killed in Bombings Aimed at Nigerian Figures",
            "url": "https://www.nytimes.com/2014/07/24/world/africa/42-are-killed-in-bombings-aimed-at-nigerian-figures.html",
            "published_date": "2014-07-24T00:17:07+0000",
            "category": "World",
            "abstract": "Officials said the terrorist bombs in the northern city of Kaduna were intended for Muhammadu Buhari, a leading politician, and Sheik Dahiru Bauchi, a cleric.",
            "image_url": null
        },
        {
            "title": "As Much of the World Frowns on Israel, Americans Hold Out Support",
            "url": "https://www.nytimes.com/2014/07/24/world/middleeast/as-much-of-the-world-frowns-on-israel-americans-hold-out-support.html",
            "published_date": "2014-07-24T01:17:58+0000",
            "category": "World",
            "abstract": "The failures of the Arab Spring to spread democracy in the Middle East have left many in America more inclined to side with Israel, which has lost backing elsewhere, analysts say.",
            "image_url": "https://www.nytimes.com/images/2014/07/24/world/SHIELDSjp01/SHIELDSjp01-articleLarge-v2.jpg"
        },
        {
            "title": "Swindlers Target Kin of Migrants",
            "url": "https://www.nytimes.com/2014/07/24/world/americas/swindles-target-kin-of-migrants.html",
            "published_date": "2014-07-24T01:29:06+0000",
            "category": "World",
            "abstract": "The F.B.I. is investigating how con artists received detailed information about migrant children being housed at military bases to lure relatives into paying hefty sums to reunite their families.",
            "image_url": "https://www.nytimes.com/images/2014/07/24/us/JP-FRAUDSTER/JP-FRAUDSTER-articleLarge.jpg"
        },
        {
            "title": "Israel Says That Hamas Uses Civilian Shields, Reviving Debate",
            "url": "https://www.nytimes.com/2014/07/24/world/middleeast/israel-says-hamas-is-using-civilians-as-shields-in-gaza.html",
            "published_date": "2014-07-24T02:00:39+0000",
            "category": "World",
            "abstract": "Israel said it takes precautions to avoid killing civilians but because its adversaries embed forces throughout Gaza, it strikes at targets where large numbers of civilian casualties are likely.",
            "image_url": "https://www.nytimes.com/images/2014/07/24/world/middleeast/SHIELDS/SHIELDS-articleLarge.jpg"
        },
        {
            "title": "Crash Victims to Undergo Routine Tests, Experts Say",
            "url": "https://www.nytimes.com/2014/07/24/science/crash-victims-to-undergo-routine-tests-experts-say.html",
            "published_date": "2014-07-24T03:32:35+0000",
            "category": "Science",
            "abstract": "Some of the testing may help illuminate exactly what happened to the jetliner after it was hit by a surface-to-air missile.",
            "image_url": null
        }
    ],
    "2014-07-25": [
        {
            "title": "Washington Post Reporter Apparently Detained in Iran",
            "url": "https://www.nytimes.com/2014/07/25/world/middleeast/washington-post-reporter-apparently-detained-in-iran.html",
            "published_date": "2014-07-25T00:08:42+0000",
            "category": "World",
            "abstract": "A Washington Post correspondent, his Iranian wife and two other Americans were apparently taken into custody on Tuesday.",
            "image_url": null
        },
        {
            "title": "Official Vents Outrage at Shelling of U.N. Schools in Gaza",
            "url": "https://www.nytimes.com/2014/07/25/world/middleeast/official-vents-outrage-at-shelling-of-un-schools-in-gaza.html",
            "published_date": "2014-07-25T00:57:00+0000",
            "category": "World",
            "abstract": "The United Nations had given the Israeli military precise GPS locations of all 83 schools that were being used as shelters for 141,000 people who had fled their homes.",
            "image_url": null
        },
        {
            "title": "Ukraine Disaster in Search of an Investigation",
            "url": "https://www.nytimes.com/2014/07/25/world/europe/ukraine-disaster-in-search-of-an-investigation.html",
            "published_date": "2014-07-25T01:46:07+0000",
            "category": "World",
            "abstract": "For all of the diplomatic frenzy that has followed the downing of Malaysia Airlines Flight 17, there is no sign of an investigation at the crash site.",
            "image_url": "https://www.nytimes.com/images/2014/07/25/world/JETPROBEjp01/JETPROBEjp01-articleLarge.jpg"
        },
        {
            "title": "Temple in Brazil Appeals to a Surge in Evangelicals",
            "url": "https://www.nytimes.com/2014/07/25/world/americas/temple-in-brazil-appeals-to-a-surge-in-evangelicals.html",
            "published_date": "2014-07-25T02:10:47+0000",
            "category": "World",
            "abstract": "A recently completed replica of a temple from biblical tradition underscores the surging growth of evangelical Christianity in Brazil, as well as the country\u2019s competitive religious landscape.",
            "image_url": "https://www.nytimes.com/images/2014/07/25/world/BRAZIL/BRAZIL-articleLarge.jpg"
        },
        {
            "title": "Kerry Proposes Weeklong Halt to Fighting in Gaza Strip",
            "url": "https://www.nytimes.com/2014/07/25/world/middleeast/kerry-proposes-weeklong-halt-to-fighting-in-gaza-strip.html",
            "published_date": "2014-07-25T02:37:30+0000",
            "category": "World",
            "abstract": "Under the plan, Palestinian and Israeli officials would cease fighting on Sunday and begin negotiations on the principal economic, political and security concerns about Gaza.",
            "image_url": null
        }
    ],
    "2014-07-26": [
        {
            "title": "Militants Said to Kill Scores at a Syrian Base ",
            "url": "https://www.nytimes.com/2014/07/26/world/europe/isis-militants-said-to-have-killed-syrian-soldiers-outside-raqqa-province.html",
            "published_date": "2014-07-26T00:07:27+0000",
            "category": "World",
            "abstract": "An activist group says ISIS killed dozens of Syrian soldiers and took over part of their base as the militants\u2019 direct clashes with the government escalate.",
            "image_url": null
        },
        {
            "title": "In Scarred Chinese Tibetan City, Devotion to Sanctity of Life",
            "url": "https://www.nytimes.com/2014/07/26/world/asia/in-scarred-chinese-tibetan-city-of-yushu-devotion-to-sanctity-of-life-even-a-tiny-river-shrimp.html",
            "published_date": "2014-07-26T00:48:48+0000",
            "category": "World",
            "abstract": "In Yushu, Buddhists demonstrate a reverence for all living beings \u2014 even a tiny river shrimp that some believe could be the reincarnated souls of loved ones who died in an earthquake in 2010.",
            "image_url": "https://www.nytimes.com/images/2014/07/26/world/YUSHU-1/YUSHU-1-articleLarge.jpg"
        },
        {
            "title": "Israel\u2019s Outspoken Envoy Is Wise to U.S. Ways",
            "url": "https://www.nytimes.com/2014/07/26/world/middleeast/israels-outspoken-envoy-is-wise-to-us-ways.html",
            "published_date": "2014-07-26T01:10:14+0000",
            "category": "World",
            "abstract": "Ambassador Ron Dermer, a former American citizen, has such a close relationship to Prime Minister Benjamin Netanyahu of Israel that he has been called \u201cBibi\u2019s brain.\u201d",
            "image_url": "https://www.nytimes.com/images/2014/07/26/world/DERMER/DERMER-articleLarge.jpg"
        },
        {
            "title": "A Ukrainian Rebel Commander Veers Off-Script",
            "url": "https://www.nytimes.com/2014/07/26/world/europe/ukrainian-rebel-commander-veers-off-script.html",
            "published_date": "2014-07-26T01:35:06+0000",
            "category": "World",
            "abstract": "A separatist commander said that the rebels did have antiaircraft missiles and might have shot down Malaysia Airlines Flight 17.",
            "image_url": null
        },
        {
            "title": "Rescuing Creatures for Good Karma",
            "url": "https://www.nytimes.com/video/world/asia/100000003009354/rescuing-creatures-for-good-karma.html",
            "published_date": "2014-07-26T01:36:34+0000",
            "category": "World",
            "abstract": "Buddhist devotees in Yushu, China, rescue tiny river fish from riverbanks as an expression of the Buddhist reverence for all forms of life and as a gesture to help in their next life.",
            "image_url": "https://www.nytimes.com/images/2014/07/18/multimedia/china-buddhist-creatures/china-buddhist-creatures-articleLarge-v2.png"
        }
    ],
    "2014-07-27": [
        {
            "title": "Israel Extends Cease-Fire in Gaza, a U.N. Request Rejected by Hamas",
            "url": "https://www.nytimes.com/2014/07/27/world/middleeast/israel-extends-cease-fire-in-gaza-a-un-request-rejected-by-hamas.html",
            "published_date": "2014-07-27T00:16:22+0000",
            "category": "World",
            "abstract": "Hamas rejected the extension of the humanitarian lull for 24 hours, and Israel said it would continue to destroy tunnels from Gaza into its territory.",
            "image_url": "https://www.nytimes.com/images/2014/07/27/world/DIPLO/DIPLO-articleLarge.jpg"
        },
        {
            "title": "In Search for Killer, DNA Sweep Exposes Intimate Family Secrets in Italy",
            "url": "https://www.nytimes.com/2014/07/27/world/europe/in-search-for-killer-dna-sweep-exposes-intimate-family-secrets-in-italy.html",
            "published_date": "2014-07-27T00:42:14+0000",
            "category": "World",
            "abstract": "The search for the killer in a sensational murder case revealed personal details about a suspect and set off a debate about the risks of privacy violations in DNA searches.",
            "image_url": "https://www.nytimes.com/images/2014/07/27/world/ITALY/ITALY-articleLarge.jpg"
        },
        {
            "title": "Israel Says Its Forces Did Not Kill Palestinians Sheltering at U.N. School",
            "url": "https://www.nytimes.com/2014/07/28/world/middleeast/israel-gaza-strip.html",
            "published_date": "2014-07-27T08:32:42+0000",
            "category": "World",
            "abstract": "Israel and Hamas went back and forth on cease-fire proposals as Israel sought to bolster its claim that it was not responsible for deaths at a United Nations school on Thursday.",
            "image_url": "https://www.nytimes.com/images/2014/07/28/world/middleeast/28ISRAEL-UN/28ISRAEL-UN-articleLarge-v2.jpg"
        },
        {
            "title": "Assessing the Damage and Destruction in Gaza",
            "url": "https://www.nytimes.com/interactive/2014/07/27/world/middleeast/assessing-the-damage-and-destruction-in-gaza.html",
            "published_date": "2014-07-27T10:54:49+0000",
            "category": "World",
            "abstract": "Analysis of satellite imagery taken before and after the first two and a half weeks of the Israeli incursion.",
            "image_url": "https://www.nytimes.com/images/2014/07/27/world/middleeast/assessing-the-damage-and-destruction-in-gaza-1406453368376/assessing-the-damage-and-destruction-in-gaza-1406453368376-articleLarge.jpg"
        },
        {
            "title": "Troops Move on Crash Site in Ukraine, Foiling Deal",
            "url": "https://www.nytimes.com/2014/07/28/world/europe/ukraine.html",
            "published_date": "2014-07-27T13:08:55+0000",
            "category": "World",
            "abstract": "The Ukrainian military\u2019s operation to recapture the plane\u2019s debris again stalled international efforts to secure the site.",
            "image_url": "https://www.nytimes.com/images/2014/07/27/world/europe/28UKRAINE/28UKRAINE-articleLarge.jpg"
        }
    ],
    "2014-07-28": [
        {
            "title": "Images Show Russian Rocket Fire, U.S. Says",
            "url": "https://www.nytimes.com/interactive/2014/07/27/world/europe/28ukraine-images-russian-rocket-fire.html",
            "published_date": "2014-07-28T00:43:33+0000",
            "category": "World",
            "abstract": "The State Department released intelligence images on Sunday and said they were evidence that Russian forces have fired into Ukraine.",
            "image_url": null
        },
        {
            "title": "Proposed Framework for Humanitarian Cease-Fire in Gaza",
            "url": "https://www.nytimes.com/interactive/2014/07/27/world/middleeast/28diplo-cease-fire-draft.html",
            "published_date": "2014-07-28T01:06:53+0000",
            "category": "World",
            "abstract": "Secretary of State John Kerry presented this draft document to Israel on Friday, but it was rejected.",
            "image_url": "https://www.nytimes.com/images/2014/07/27/world/middleeast/28diplo-cease-fire-draft-1406560676043/28diplo-cease-fire-draft-1406560676043-jumbo.png"
        },
        {
            "title": "Justice Dept. Moves to Shield Anti-Iran Group\u2019s Files",
            "url": "https://www.nytimes.com/2014/07/28/us/politics/us-justice-dept-moves-to-shield-anti-iran-groups-files-united-against-nuclear-iran.html",
            "published_date": "2014-07-28T01:12:31+0000",
            "category": "U.S.",
            "abstract": "The unusual move raised questions about connections between the American government and United Against Nuclear Iran, a hard-line voice seeking to prevent Iran from obtaining nuclear weapons.",
            "image_url": null
        },
        {
            "title": "Even Gaza Truce Is Hard to Win, Kerry Is Finding",
            "url": "https://www.nytimes.com/2014/07/28/world/middleeast/kerry-finds-even-a-truce-in-gaza-is-hard-to-win-cease-fire-hamas.html",
            "published_date": "2014-07-28T01:24:05+0000",
            "category": "World",
            "abstract": "Israel and Hamas both see reasons to continue fighting, and Israeli officials appear dismissive of John Kerry\u2019s aims in a way that few American secretaries of state have faced.",
            "image_url": "https://www.nytimes.com/images/2014/07/28/world/DIPLO/DIPLO-articleLarge.jpg"
        },
        {
            "title": "Why Ebola Patients Are Rejecting Care",
            "url": "https://www.nytimes.com/video/world/africa/100000003019972/why-ebola-patients-are-rejecting-care.html",
            "published_date": "2014-07-28T01:58:40+0000",
            "category": "World",
            "abstract": "Amid the deadliest Ebola virus outbreak in history, doctors are fighting the disease and also local populations\u2019 fear of medical treatment.",
            "image_url": "https://www.nytimes.com/images/2014/07/24/multimedia/ebola-outbreak/ebola-outbreak-articleLarge.jpg"
        }
    ],
    "2014-07-29": [
        {
            "title": "Fuel Depot Fire Endangers Civilians in Libya",
            "url": "https://www.nytimes.com/2014/07/29/world/africa/fuel-depot-fire-endangers-civilians-in-libya.html",
            "published_date": "2014-07-29T00:06:46+0000",
            "category": "World",
            "abstract": "Two storage tanks are ablaze in the fire, which was started by militias fighting for control of the airport in Tripoli.",
            "image_url": "https://www.nytimes.com/images/2014/07/29/world/29LIBYA/29LIBYA-articleLarge.jpg"
        },
        {
            "title": "Boko Haram Targets Political Figures in String of Attacks",
            "url": "https://www.nytimes.com/2014/07/29/world/africa/boko-haram-targets-political-figures-in-string-of-attacks.html",
            "published_date": "2014-07-29T00:58:29+0000",
            "category": "World",
            "abstract": "The terrorist group has attacked or kidnapped prominent citizens in Cameroon and Nigeria, and has committed a series of suicide bombings that have killed at least 11 over two days.",
            "image_url": null
        },
        {
            "title": "Venezuelan Officers Linked to Colombian Cocaine Traffickers",
            "url": "https://www.nytimes.com/2014/07/29/world/americas/venezuelan-officers-linked-to-colombian-cocaine-traffickers.html",
            "published_date": "2014-07-29T01:13:48+0000",
            "category": "World",
            "abstract": "The head of Venezuelan military intelligence was on the payroll of a Colombian drug lord, invested money in drug shipments and coordinated the shipment of cocaine, according to prosecutors.",
            "image_url": "https://www.nytimes.com/images/2014/07/29/world/VENEZUELA/VENEZUELA-articleLarge.jpg"
        },
        {
            "title": "Tunnels Lead Right to the Heart of Israeli Fear",
            "url": "https://www.nytimes.com/2014/07/29/world/middleeast/tunnels-lead-right-to-heart-of-israeli-fear.html",
            "published_date": "2014-07-29T01:47:50+0000",
            "category": "World",
            "abstract": "The sophistication and extent of the underground passages used by Hamas to infiltrate Israel from Gaza has stiffened Israeli resolve to destroy them.",
            "image_url": null
        },
        {
            "title": "Short Staff Tries to Cope With Ebola",
            "url": "https://www.nytimes.com/2014/07/29/world/africa/short-staff-tries-to-cope-with-ebola.html",
            "published_date": "2014-07-29T02:07:42+0000",
            "category": "World",
            "abstract": "As an outbreak worsened, a pay dispute with nurses left a short staff able to care primarily for just the sickest patients who had a chance of surviving.",
            "image_url": null
        }
    ],
    "2014-07-30": [
        {
            "title": "Loss of Shelter and Electricity Worsens a Crisis for Fleeing Gazans",
            "url": "https://www.nytimes.com/2014/07/30/world/middleeast/loss-of-shelter-and-electricity-worsens-a-crisis-for-fleeing-gazans.html",
            "published_date": "2014-07-30T00:31:04+0000",
            "category": "World",
            "abstract": "Three weeks of war between Israel and Palestinian militants in Gaza have pushed the territory to the brink of humanitarian disaster.",
            "image_url": "https://www.nytimes.com/images/2014/07/30/world/GAZA02/GAZA02-articleLarge.jpg"
        },
        {
            "title": "Lawmakers Voice Skepticism on Iran Nuclear Deal",
            "url": "https://www.nytimes.com/2014/07/30/world/middleeast/lawmakers-voice-skepticism-on-iran-nuclear-deal.html",
            "published_date": "2014-07-30T01:16:22+0000",
            "category": "World",
            "abstract": "If an accord is reached, it would not be a formal treaty, so the Senate would not be called upon to ratify it.",
            "image_url": null
        },
        {
            "title": "As Sanctions Pile Up, Russians\u2019 Alarm Grows Over Putin\u2019s Tactics",
            "url": "https://www.nytimes.com/2014/07/30/world/europe/as-sanctions-pile-up-russians-alarm-grows-over-putin-tactics.html",
            "published_date": "2014-07-30T02:28:31+0000",
            "category": "World",
            "abstract": "Fears are growing that the festering turmoil in Ukraine and the new round of sanctions announced Tuesday will damage the economy to the extent that ordinary Russians feel it.",
            "image_url": "https://www.nytimes.com/images/2014/07/30/world/PUTINjp/PUTINjp-articleLarge-v2.jpg"
        },
        {
            "title": "Honoring a Filmmaker in the Shadow of Apartheid",
            "url": "https://www.nytimes.com/2014/07/30/world/africa/honoring-a-filmmaker-in-the-shadow-of-apartheid.html",
            "published_date": "2014-07-30T02:43:22+0000",
            "category": "World",
            "abstract": "Although he did not oppose apartheid, Tonie van der Merwe created movies exclusively for blacks, launching the careers of many actors and technicians in the \u201970s and \u201980s.",
            "image_url": "https://www.nytimes.com/images/2014/07/30/world/30SAFRICA01/30SAFRICA01-articleLarge.jpg"
        },
        {
            "title": "North Korea: Images Show Work on Rocket Site",
            "url": "https://www.nytimes.com/2014/07/30/world/asia/north-korea-images-show-work-on-rocket-site.html",
            "published_date": "2014-07-30T03:03:59+0000",
            "category": "World",
            "abstract": "North Korea has nearly completed construction of an improved site for launching long-range missiles and appears to have conducted multiple tests of rocket motors for them.",
            "image_url": null
        }
    ],
    "2014-07-31": [
        {
            "title": "U.S. Bars Travel by Top Venezuelan Officials",
            "url": "https://www.nytimes.com/2014/07/31/world/americas/us-bars-travel-by-top-venezuelan-officials.html",
            "published_date": "2014-07-31T00:49:08+0000",
            "category": "World",
            "abstract": "Limits affecting cabinet members, agency heads, mayors, judges, and members of the military and the police were imposed in response to human rights abuses by the Venezuelan government at antigovernment demonstrations.",
            "image_url": null
        },
        {
            "title": "Filling Stomachs to Open Minds on Immigration",
            "url": "https://www.nytimes.com/2014/07/31/world/europe/in-sweden-dinners-melt-cultural-barriers.html",
            "published_date": "2014-07-31T01:04:34+0000",
            "category": "World",
            "abstract": "To combat the anti-immigrant sentiment in Sweden, a young teacher has begun hosting communal dinners to help bridge the gap between cultures.",
            "image_url": "https://www.nytimes.com/images/2014/07/31/world/31STOCKHOLM/31STOCKHOLM-articleLarge.jpg"
        },
        {
            "title": "Suicide Bomber From U.S. Came Home Before Attack",
            "url": "https://www.nytimes.com/2014/07/31/us/suicide-bomber-from-us-came-home-before-attack.html",
            "published_date": "2014-07-31T01:48:59+0000",
            "category": "U.S.",
            "abstract": "Moner Mohammad Abusalha, a Florida man who died in a suicide attack in Syria in May, traveled to the U.S. for several months after training with a group allied with Al Qaeda.",
            "image_url": "https://www.nytimes.com/images/2014/07/31/world/31bomber_inline/31bomber_inline-articleLarge.jpg"
        },
        {
            "title": "Quest for Demilitarization of Gaza Is Seen Getting Netanyahu Only So Far",
            "url": "https://www.nytimes.com/2014/07/31/world/middleeast/quest-for-demilitarization-of-gaza-is-seen-getting-netanyahu-only-so-far.html",
            "published_date": "2014-07-31T01:53:43+0000",
            "category": "World",
            "abstract": "Prime Minister Benjamin Netanyahu has begun talking about Gaza\u2019s need for \u201csocial and economic relief\u201d from decade-old Israeli restrictions on trade and travel.",
            "image_url": null
        },
        {
            "title": "Video Released of U.S. Bomber in Syria",
            "url": "https://www.nytimes.com/video/world/middleeast/100000003029549/video-of-us-bomber-moner-mohammad-abusalha-in-syria.html",
            "published_date": "2014-07-31T02:22:08+0000",
            "category": "World",
            "abstract": "Jihadist video released from Syria featuring an American suicide bomber, Moner Mohammad Abusalha, provides new details into his mind-set before he died in an attack in May.",
            "image_url": "https://www.nytimes.com/images/2014/07/30/multimedia/syria-bomber-florida/syria-bomber-florida-articleLarge.jpg"
        }
    ]
}